{"meta": {"total_games": 122, "last_updated": "2026-07-15 20:10 UTC", "current_patch": "16.14", "ddragon_version": "16.14.1", "player_count": 20}, "regions": {"kr": {"TOP": [{"name": "KSante", "count": 6, "pick_rate": 9.7, "win_rate": 83.3, "ban_rate": 6.5, "kda": 3.05, "top_items": [3111, 3143, 6665], "context_builds": {}}, {"name": "DrMundo", "count": 5, "pick_rate": 8.1, "win_rate": 60.0, "ban_rate": 0.0, "kda": 2.2, "top_items": [3065, 3083, 3084], "context_builds": {}}, {"name": "Jayce", "count": 5, "pick_rate": 8.1, "win_rate": 60.0, "ban_rate": 30.6, "kda": 2.0, "top_items": [3047, 3142], "context_builds": {}}, {"name": "Jax", "count": 5, "pick_rate": 8.1, "win_rate": 40.0, "ban_rate": 9.7, "kda": 1.14, "top_items": [3047, 3078, 6610], "context_builds": {}}, {"name": "Ambessa", "count": 4, "pick_rate": 6.5, "win_rate": 25.0, "ban_rate": 1.6, "kda": 2.82, "top_items": [3156, 3161, 6692], "context_builds": {}}, {"name": "Rumble", "count": 4, "pick_rate": 6.5, "win_rate": 50.0, "ban_rate": 8.1, "kda": 1.5, "top_items": [3047, 6653], "context_builds": {}}, {"name": "Gangplank", "count": 3, "pick_rate": 4.8, "win_rate": 33.3, "ban_rate": 4.8, "kda": 2.05, "top_items": [3508, 6673, 6676], "context_builds": {}}, {"name": "Cassiopeia", "count": 3, "pick_rate": 4.8, "win_rate": 66.7, "ban_rate": 9.7, "kda": 1.86, "top_items": [2503, 3116, 4646], "context_builds": {}}, {"name": "Swain", "count": 2, "pick_rate": 3.2, "win_rate": 50.0, "ban_rate": 0.0, "kda": 1.83, "top_items": [3009, 3116], "context_builds": {}}, {"name": "Pantheon", "count": 2, "pick_rate": 3.2, "win_rate": 100.0, "ban_rate": 3.2, "kda": 2.6, "top_items": [3047, 3071, 6610], "context_builds": {}}, {"name": "Nidalee", "count": 2, "pick_rate": 3.2, "win_rate": 0.0, "ban_rate": 29.0, "kda": 0.78, "top_items": [3047, 3078, 6610], "context_builds": {}}, {"name": "Vayne", "count": 2, "pick_rate": 3.2, "win_rate": 50.0, "ban_rate": 11.3, "kda": 0.83, "top_items": [3006, 3073, 3508], "context_builds": {}}, {"name": "Gnar", "count": 2, "pick_rate": 3.2, "win_rate": 50.0, "ban_rate": 0.0, "kda": 1.18, "top_items": [3047, 3091, 3143], "context_builds": {}}, {"name": "Garen", "count": 1, "pick_rate": 1.6, "win_rate": 0.0, "ban_rate": 3.2, "kda": 1.6, "top_items": [3142, 3742, 6631], "context_builds": {}}, {"name": "Zaahen", "count": 1, "pick_rate": 1.6, "win_rate": 0.0, "ban_rate": 0.0, "kda": 0.5, "top_items": [3158, 6631], "context_builds": {}}], "JUNGLE": [{"name": "LeeSin", "count": 11, "pick_rate": 17.7, "win_rate": 27.3, "ban_rate": 38.7, "kda": 2.34, "top_items": [6333, 6610, 6692], "context_builds": {"Tank Heavy": {"games": 3, "items": [3111, 6692]}}}, {"name": "Qiyana", "count": 5, "pick_rate": 8.1, "win_rate": 60.0, "ban_rate": 9.7, "kda": 3.81, "top_items": [6694, 6698, 6699], "context_builds": {}}, {"name": "Hecarim", "count": 5, "pick_rate": 8.1, "win_rate": 40.0, "ban_rate": 1.6, "kda": 3.38, "top_items": [3026, 3161, 6333], "context_builds": {}}, {"name": "Naafiri", "count": 4, "pick_rate": 6.5, "win_rate": 75.0, "ban_rate": 11.3, "kda": 5.8, "top_items": [3071, 6699], "context_builds": {}}, {"name": "JarvanIV", "count": 4, "pick_rate": 6.5, "win_rate": 0.0, "ban_rate": 0.0, "kda": 1.58, "top_items": [3047, 3161, 6610], "context_builds": {}}, {"name": "Vi", "count": 3, "pick_rate": 4.8, "win_rate": 0.0, "ban_rate": 0.0, "kda": 2.71, "top_items": [3026, 3071, 6610], "context_builds": {}}, {"name": "Belveth", "count": 3, "pick_rate": 4.8, "win_rate": 33.3, "ban_rate": 11.3, "kda": 3.75, "top_items": [3111, 3190, 6631], "context_builds": {}}, {"name": "MasterYi", "count": 2, "pick_rate": 3.2, "win_rate": 0.0, "ban_rate": 0.0, "kda": 0.71, "top_items": [3008, 3124, 6672], "context_builds": {}}, {"name": "Nocturne", "count": 2, "pick_rate": 3.2, "win_rate": 50.0, "ban_rate": 0.0, "kda": 1.92, "top_items": [3073, 6333, 6631], "context_builds": {}}, {"name": "Kayn", "count": 2, "pick_rate": 3.2, "win_rate": 100.0, "ban_rate": 0.0, "kda": 2.65, "top_items": [3071, 6333, 6699], "context_builds": {}}, {"name": "Elise", "count": 2, "pick_rate": 3.2, "win_rate": 50.0, "ban_rate": 0.0, "kda": 4.5, "top_items": [3020, 3157, 4645], "context_builds": {}}, {"name": "Kindred", "count": 2, "pick_rate": 3.2, "win_rate": 100.0, "ban_rate": 4.8, "kda": 4.4, "top_items": [3006, 6672, 6676], "context_builds": {}}, {"name": "Nidalee", "count": 2, "pick_rate": 3.2, "win_rate": 100.0, "ban_rate": 29.0, "kda": 5.15, "top_items": [3100, 3157, 4645], "context_builds": {}}, {"name": "Locke", "count": 2, "pick_rate": 3.2, "win_rate": 50.0, "ban_rate": 101.6, "kda": 3.88, "top_items": [3100, 3135, 4646], "context_builds": {}}, {"name": "Aatrox", "count": 1, "pick_rate": 1.6, "win_rate": 0.0, "ban_rate": 0.0, "kda": 2.43, "top_items": [6333, 6610, 6699], "context_builds": {}}], "MIDDLE": [{"name": "Orianna", "count": 5, "pick_rate": 8.1, "win_rate": 20.0, "ban_rate": 3.2, "kda": 2.06, "top_items": [3152, 3175, 6655], "context_builds": {}}, {"name": "Locke", "count": 5, "pick_rate": 8.1, "win_rate": 60.0, "ban_rate": 101.6, "kda": 4.18, "top_items": [3157, 3175, 4645], "context_builds": {}}, {"name": "Akali", "count": 5, "pick_rate": 8.1, "win_rate": 60.0, "ban_rate": 11.3, "kda": 2.57, "top_items": [3146, 3173, 4645], "context_builds": {}}, {"name": "Cassiopeia", "count": 4, "pick_rate": 6.5, "win_rate": 75.0, "ban_rate": 9.7, "kda": 1.54, "top_items": [3168, 4629], "context_builds": {}}, {"name": "Yone", "count": 4, "pick_rate": 6.5, "win_rate": 50.0, "ban_rate": 0.0, "kda": 2.85, "top_items": [3153, 3172, 6673], "context_builds": {}}, {"name": "Sylas", "count": 3, "pick_rate": 4.8, "win_rate": 0.0, "ban_rate": 9.7, "kda": 1.92, "top_items": [3152, 3157, 3171], "context_builds": {}}, {"name": "Zoe", "count": 3, "pick_rate": 4.8, "win_rate": 33.3, "ban_rate": 25.8, "kda": 7.0, "top_items": [3100, 3157, 3175], "context_builds": {}}, {"name": "Yasuo", "count": 3, "pick_rate": 4.8, "win_rate": 0.0, "ban_rate": 9.7, "kda": 1.43, "top_items": [3172, 6672, 6673], "context_builds": {}}, {"name": "Syndra", "count": 3, "pick_rate": 4.8, "win_rate": 66.7, "ban_rate": 16.1, "kda": 1.47, "top_items": [3152, 3171, 4645], "context_builds": {}}, {"name": "Akshan", "count": 2, "pick_rate": 3.2, "win_rate": 50.0, "ban_rate": 1.6, "kda": 0.91, "top_items": [3033, 6673, 6676], "context_builds": {}}, {"name": "Ryze", "count": 2, "pick_rate": 3.2, "win_rate": 50.0, "ban_rate": 1.6, "kda": 1.3, "top_items": [3170, 6657], "context_builds": {}}, {"name": "TwistedFate", "count": 2, "pick_rate": 3.2, "win_rate": 0.0, "ban_rate": 6.5, "kda": 2.58, "top_items": [3100, 3170, 6657], "context_builds": {}}, {"name": "Tristana", "count": 2, "pick_rate": 3.2, "win_rate": 100.0, "ban_rate": 0.0, "kda": 2.31, "top_items": [3173, 6672, 6675], "context_builds": {}}, {"name": "Galio", "count": 2, "pick_rate": 3.2, "win_rate": 50.0, "ban_rate": 3.2, "kda": 3.0, "top_items": [3152, 3173, 4005], "context_builds": {}}, {"name": "Qiyana", "count": 2, "pick_rate": 3.2, "win_rate": 50.0, "ban_rate": 9.7, "kda": 1.7, "top_items": [3171, 6698], "context_builds": {}}], "BOTTOM": [{"name": "Syndra", "count": 7, "pick_rate": 11.3, "win_rate": 57.1, "ban_rate": 16.1, "kda": 2.4, "top_items": [3152, 4645, 6655], "context_builds": {}}, {"name": "Yunara", "count": 5, "pick_rate": 8.1, "win_rate": 40.0, "ban_rate": 0.0, "kda": 3.09, "top_items": [3036, 6672, 6673], "context_builds": {}}, {"name": "Jhin", "count": 5, "pick_rate": 8.1, "win_rate": 20.0, "ban_rate": 0.0, "kda": 2.15, "top_items": [3094, 3097, 6697], "context_builds": {"Tank Heavy": {"games": 3, "items": [3046, 6697]}}}, {"name": "Ziggs", "count": 4, "pick_rate": 6.5, "win_rate": 25.0, "ban_rate": 3.2, "kda": 1.73, "top_items": [3157, 4645, 6655], "context_builds": {}}, {"name": "Ezreal", "count": 4, "pick_rate": 6.5, "win_rate": 50.0, "ban_rate": 16.1, "kda": 2.43, "top_items": [2517, 3161, 6694], "context_builds": {}}, {"name": "Kaisa", "count": 4, "pick_rate": 6.5, "win_rate": 75.0, "ban_rate": 0.0, "kda": 3.35, "top_items": [3115, 3124, 6672], "context_builds": {}}, {"name": "Sivir", "count": 3, "pick_rate": 4.8, "win_rate": 33.3, "ban_rate": 0.0, "kda": 2.47, "top_items": [3033, 3508, 6675], "context_builds": {}}, {"name": "Lucian", "count": 3, "pick_rate": 4.8, "win_rate": 66.7, "ban_rate": 1.6, "kda": 2.4, "top_items": [3508, 6675], "context_builds": {}}, {"name": "Sylas", "count": 3, "pick_rate": 4.8, "win_rate": 0.0, "ban_rate": 9.7, "kda": 1.36, "top_items": [3152, 4646], "context_builds": {}}, {"name": "Viktor", "count": 3, "pick_rate": 4.8, "win_rate": 66.7, "ban_rate": 0.0, "kda": 2.55, "top_items": [3135, 3152, 6653], "context_builds": {}}, {"name": "Hwei", "count": 3, "pick_rate": 4.8, "win_rate": 33.3, "ban_rate": 1.6, "kda": 1.88, "top_items": [2503, 3135, 3152], "context_builds": {}}, {"name": "Xerath", "count": 3, "pick_rate": 4.8, "win_rate": 66.7, "ban_rate": 8.1, "kda": 2.0, "top_items": [4646, 6655], "context_builds": {}}, {"name": "Ashe", "count": 3, "pick_rate": 4.8, "win_rate": 33.3, "ban_rate": 3.2, "kda": 1.76, "top_items": [2523, 3033, 3046], "context_builds": {}}, {"name": "Cassiopeia", "count": 2, "pick_rate": 3.2, "win_rate": 50.0, "ban_rate": 9.7, "kda": 0.71, "top_items": [2503, 3116], "context_builds": {}}, {"name": "Jayce", "count": 2, "pick_rate": 3.2, "win_rate": 50.0, "ban_rate": 30.6, "kda": 1.69, "top_items": [3142, 6699], "context_builds": {}}], "UTILITY": [{"name": "Camille", "count": 11, "pick_rate": 17.7, "win_rate": 36.4, "ban_rate": 59.7, "kda": 1.93, "top_items": [3111, 6610], "context_builds": {}}, {"name": "Pyke", "count": 9, "pick_rate": 14.5, "win_rate": 44.4, "ban_rate": 45.2, "kda": 2.0, "top_items": [3009, 3814, 6699], "context_builds": {}}, {"name": "Pantheon", "count": 5, "pick_rate": 8.1, "win_rate": 40.0, "ban_rate": 3.2, "kda": 1.4, "top_items": [3111, 6610], "context_builds": {}}, {"name": "Bard", "count": 5, "pick_rate": 8.1, "win_rate": 40.0, "ban_rate": 24.2, "kda": 1.44, "top_items": [3111, 3190, 3222], "context_builds": {}}, {"name": "Shen", "count": 5, "pick_rate": 8.1, "win_rate": 40.0, "ban_rate": 3.2, "kda": 2.94, "top_items": [2525, 3158, 3190], "context_builds": {}}, {"name": "Nautilus", "count": 4, "pick_rate": 6.5, "win_rate": 50.0, "ban_rate": 8.1, "kda": 3.24, "top_items": [2525, 3047, 3109], "context_builds": {}}, {"name": "Leona", "count": 3, "pick_rate": 4.8, "win_rate": 100.0, "ban_rate": 1.6, "kda": 5.0, "top_items": [2524, 3111, 3190], "context_builds": {}}, {"name": "Nami", "count": 2, "pick_rate": 3.2, "win_rate": 50.0, "ban_rate": 0.0, "kda": 6.86, "top_items": [3158, 6617, 6620], "context_builds": {}}, {"name": "Sylas", "count": 2, "pick_rate": 3.2, "win_rate": 50.0, "ban_rate": 9.7, "kda": 1.41, "top_items": [3020, 3152], "context_builds": {}}, {"name": "Taric", "count": 1, "pick_rate": 1.6, "win_rate": 0.0, "ban_rate": 0.0, "kda": 1.75, "top_items": [3158, 3190], "context_builds": {}}, {"name": "Ambessa", "count": 1, "pick_rate": 1.6, "win_rate": 100.0, "ban_rate": 1.6, "kda": 2.2, "top_items": [3111, 3161, 6692], "context_builds": {}}, {"name": "Elise", "count": 1, "pick_rate": 1.6, "win_rate": 100.0, "ban_rate": 0.0, "kda": 4.75, "top_items": [3020, 4005], "context_builds": {}}, {"name": "Thresh", "count": 1, "pick_rate": 1.6, "win_rate": 100.0, "ban_rate": 1.6, "kda": 3.6, "top_items": [2525, 3109, 3190], "context_builds": {}}, {"name": "Lulu", "count": 1, "pick_rate": 1.6, "win_rate": 100.0, "ban_rate": 1.6, "kda": 6.25, "top_items": [2065, 3158, 3504], "context_builds": {}}, {"name": "Karma", "count": 1, "pick_rate": 1.6, "win_rate": 0.0, "ban_rate": 3.2, "kda": 1.67, "top_items": [3158, 3222, 6620], "context_builds": {}}]}, "euw1": {"TOP": [{"name": "Jayce", "count": 8, "pick_rate": 13.3, "win_rate": 62.5, "ban_rate": 28.3, "kda": 2.71, "top_items": [3111, 3142], "context_builds": {}}, {"name": "Ambessa", "count": 5, "pick_rate": 8.3, "win_rate": 80.0, "ban_rate": 8.3, "kda": 3.55, "top_items": [3047, 3161, 6692], "context_builds": {}}, {"name": "Vayne", "count": 4, "pick_rate": 6.7, "win_rate": 0.0, "ban_rate": 15.0, "kda": 0.97, "top_items": [3006, 3073, 3078], "context_builds": {}}, {"name": "Vladimir", "count": 3, "pick_rate": 5.0, "win_rate": 66.7, "ban_rate": 11.7, "kda": 3.33, "top_items": [3152, 3158], "context_builds": {}}, {"name": "Fiora", "count": 3, "pick_rate": 5.0, "win_rate": 66.7, "ban_rate": 6.7, "kda": 2.47, "top_items": [3074, 3078], "context_builds": {}}, {"name": "Aurora", "count": 3, "pick_rate": 5.0, "win_rate": 100.0, "ban_rate": 1.7, "kda": 1.73, "top_items": [3158, 4629, 6653], "context_builds": {}}, {"name": "Varus", "count": 2, "pick_rate": 3.3, "win_rate": 50.0, "ban_rate": 5.0, "kda": 0.9, "top_items": [3009, 3073], "context_builds": {}}, {"name": "Renekton", "count": 2, "pick_rate": 3.3, "win_rate": 0.0, "ban_rate": 3.3, "kda": 0.31, "top_items": [], "context_builds": {}}, {"name": "Annie", "count": 2, "pick_rate": 3.3, "win_rate": 100.0, "ban_rate": 18.3, "kda": 2.18, "top_items": [2503, 3158, 6653], "context_builds": {}}, {"name": "Ornn", "count": 2, "pick_rate": 3.3, "win_rate": 100.0, "ban_rate": 1.7, "kda": 2.2, "top_items": [2502, 3047, 3050], "context_builds": {}}, {"name": "Yone", "count": 2, "pick_rate": 3.3, "win_rate": 100.0, "ban_rate": 0.0, "kda": 3.73, "top_items": [3006, 3153, 6673], "context_builds": {}}, {"name": "KSante", "count": 2, "pick_rate": 3.3, "win_rate": 50.0, "ban_rate": 1.7, "kda": 1.56, "top_items": [3075, 3111, 6662], "context_builds": {}}, {"name": "Malphite", "count": 1, "pick_rate": 1.7, "win_rate": 0.0, "ban_rate": 21.7, "kda": 0.67, "top_items": [], "context_builds": {}}, {"name": "Rengar", "count": 1, "pick_rate": 1.7, "win_rate": 0.0, "ban_rate": 16.7, "kda": 3.57, "top_items": [3036, 3047, 3074], "context_builds": {}}, {"name": "Garen", "count": 1, "pick_rate": 1.7, "win_rate": 100.0, "ban_rate": 0.0, "kda": 0.9, "top_items": [3009, 3046, 6631], "context_builds": {}}], "JUNGLE": [{"name": "Viego", "count": 4, "pick_rate": 6.7, "win_rate": 50.0, "ban_rate": 0.0, "kda": 2.48, "top_items": [3111, 6333, 6673], "context_builds": {}}, {"name": "Khazix", "count": 4, "pick_rate": 6.7, "win_rate": 75.0, "ban_rate": 1.7, "kda": 2.44, "top_items": [3179, 3814, 6699], "context_builds": {}}, {"name": "Qiyana", "count": 3, "pick_rate": 5.0, "win_rate": 33.3, "ban_rate": 13.3, "kda": 3.42, "top_items": [6694, 6698, 6699], "context_builds": {}}, {"name": "JarvanIV", "count": 3, "pick_rate": 5.0, "win_rate": 66.7, "ban_rate": 0.0, "kda": 4.08, "top_items": [6333, 6610, 6698], "context_builds": {}}, {"name": "MonkeyKing", "count": 3, "pick_rate": 5.0, "win_rate": 33.3, "ban_rate": 0.0, "kda": 1.73, "top_items": [3078, 3111, 6610], "context_builds": {}}, {"name": "DrMundo", "count": 3, "pick_rate": 5.0, "win_rate": 66.7, "ban_rate": 1.7, "kda": 3.88, "top_items": [2504, 3009, 3084], "context_builds": {}}, {"name": "Hecarim", "count": 3, "pick_rate": 5.0, "win_rate": 0.0, "ban_rate": 5.0, "kda": 1.86, "top_items": [3158, 3161, 6333], "context_builds": {}}, {"name": "Naafiri", "count": 2, "pick_rate": 3.3, "win_rate": 0.0, "ban_rate": 16.7, "kda": 1.5, "top_items": [3071, 6699], "context_builds": {}}, {"name": "Aatrox", "count": 2, "pick_rate": 3.3, "win_rate": 50.0, "ban_rate": 1.7, "kda": 3.07, "top_items": [3033, 3047, 6697], "context_builds": {}}, {"name": "Rengar", "count": 2, "pick_rate": 3.3, "win_rate": 50.0, "ban_rate": 16.7, "kda": 2.23, "top_items": [3036, 3142, 6698], "context_builds": {}}, {"name": "Nocturne", "count": 2, "pick_rate": 3.3, "win_rate": 50.0, "ban_rate": 1.7, "kda": 3.38, "top_items": [3073, 3111, 6631], "context_builds": {}}, {"name": "Shaco", "count": 2, "pick_rate": 3.3, "win_rate": 100.0, "ban_rate": 46.7, "kda": 10.33, "top_items": [3026, 3142, 3179], "context_builds": {}}, {"name": "LeeSin", "count": 2, "pick_rate": 3.3, "win_rate": 100.0, "ban_rate": 6.7, "kda": 9.5, "top_items": [6610, 6692], "context_builds": {}}, {"name": "Pantheon", "count": 2, "pick_rate": 3.3, "win_rate": 100.0, "ban_rate": 0.0, "kda": 5.14, "top_items": [3047, 3071, 6610], "context_builds": {}}, {"name": "Talon", "count": 2, "pick_rate": 3.3, "win_rate": 50.0, "ban_rate": 21.7, "kda": 2.08, "top_items": [3179, 6695, 6699], "context_builds": {}}], "MIDDLE": [{"name": "Locke", "count": 7, "pick_rate": 11.7, "win_rate": 42.9, "ban_rate": 96.7, "kda": 2.98, "top_items": [3100, 3157, 4645], "context_builds": {}}, {"name": "Yone", "count": 5, "pick_rate": 8.3, "win_rate": 40.0, "ban_rate": 0.0, "kda": 1.9, "top_items": [3153, 3172, 6673], "context_builds": {}}, {"name": "Syndra", "count": 4, "pick_rate": 6.7, "win_rate": 75.0, "ban_rate": 33.3, "kda": 3.17, "top_items": [3137, 3175, 4629], "context_builds": {}}, {"name": "Akali", "count": 3, "pick_rate": 5.0, "win_rate": 0.0, "ban_rate": 25.0, "kda": 2.08, "top_items": [3146, 3175, 4645], "context_builds": {}}, {"name": "Aurora", "count": 3, "pick_rate": 5.0, "win_rate": 0.0, "ban_rate": 1.7, "kda": 1.8, "top_items": [3157, 3175, 4646], "context_builds": {}}, {"name": "Anivia", "count": 3, "pick_rate": 5.0, "win_rate": 33.3, "ban_rate": 3.3, "kda": 2.46, "top_items": [2522, 3171, 6657], "context_builds": {}}, {"name": "Sylas", "count": 3, "pick_rate": 5.0, "win_rate": 100.0, "ban_rate": 23.3, "kda": 5.33, "top_items": [3152, 3171, 4633], "context_builds": {}}, {"name": "Jayce", "count": 2, "pick_rate": 3.3, "win_rate": 50.0, "ban_rate": 28.3, "kda": 3.4, "top_items": [3004, 3170, 3179], "context_builds": {}}, {"name": "Irelia", "count": 2, "pick_rate": 3.3, "win_rate": 100.0, "ban_rate": 23.3, "kda": 2.86, "top_items": [3153, 3174], "context_builds": {}}, {"name": "Ekko", "count": 2, "pick_rate": 3.3, "win_rate": 100.0, "ban_rate": 8.3, "kda": 10.0, "top_items": [2510, 3175], "context_builds": {}}, {"name": "Galio", "count": 2, "pick_rate": 3.3, "win_rate": 50.0, "ban_rate": 1.7, "kda": 3.56, "top_items": [3152, 3173, 4005], "context_builds": {}}, {"name": "Cassiopeia", "count": 2, "pick_rate": 3.3, "win_rate": 50.0, "ban_rate": 11.7, "kda": 0.96, "top_items": [3116, 3157, 3170], "context_builds": {}}, {"name": "Veigar", "count": 2, "pick_rate": 3.3, "win_rate": 50.0, "ban_rate": 0.0, "kda": 3.7, "top_items": [3137, 3152, 3173], "context_builds": {}}, {"name": "TwistedFate", "count": 2, "pick_rate": 3.3, "win_rate": 100.0, "ban_rate": 0.0, "kda": 4.43, "top_items": [3094, 3100, 3152], "context_builds": {}}, {"name": "Smolder", "count": 2, "pick_rate": 3.3, "win_rate": 50.0, "ban_rate": 0.0, "kda": 3.0, "top_items": [3094, 3170, 3508], "context_builds": {}}], "BOTTOM": [{"name": "Ezreal", "count": 6, "pick_rate": 10.0, "win_rate": 50.0, "ban_rate": 21.7, "kda": 3.08, "top_items": [2517, 3078, 3161], "context_builds": {"Tank Heavy": {"games": 4, "items": [2517, 3078, 3161]}}}, {"name": "Syndra", "count": 6, "pick_rate": 10.0, "win_rate": 50.0, "ban_rate": 33.3, "kda": 1.65, "top_items": [2503, 4629], "context_builds": {}}, {"name": "Mel", "count": 4, "pick_rate": 6.7, "win_rate": 75.0, "ban_rate": 30.0, "kda": 2.21, "top_items": [3152, 6655], "context_builds": {}}, {"name": "Ziggs", "count": 3, "pick_rate": 5.0, "win_rate": 33.3, "ban_rate": 3.3, "kda": 4.55, "top_items": [3165, 4645, 6655], "context_builds": {}}, {"name": "Jinx", "count": 3, "pick_rate": 5.0, "win_rate": 100.0, "ban_rate": 0.0, "kda": 3.62, "top_items": [2523, 3085], "context_builds": {}}, {"name": "Vayne", "count": 2, "pick_rate": 3.3, "win_rate": 50.0, "ban_rate": 15.0, "kda": 4.62, "top_items": [3036, 3097, 6672], "context_builds": {}}, {"name": "Draven", "count": 2, "pick_rate": 3.3, "win_rate": 100.0, "ban_rate": 30.0, "kda": 3.13, "top_items": [2523, 3033, 3072], "context_builds": {}}, {"name": "Yasuo", "count": 2, "pick_rate": 3.3, "win_rate": 100.0, "ban_rate": 20.0, "kda": 2.31, "top_items": [3036, 6333, 6672], "context_builds": {}}, {"name": "Kaisa", "count": 2, "pick_rate": 3.3, "win_rate": 50.0, "ban_rate": 0.0, "kda": 2.56, "top_items": [3087, 3124], "context_builds": {}}, {"name": "Samira", "count": 2, "pick_rate": 3.3, "win_rate": 50.0, "ban_rate": 1.7, "kda": 1.62, "top_items": [3036, 6676], "context_builds": {}}, {"name": "Caitlyn", "count": 2, "pick_rate": 3.3, "win_rate": 50.0, "ban_rate": 3.3, "kda": 2.31, "top_items": [2523, 3036, 6673], "context_builds": {}}, {"name": "Jhin", "count": 2, "pick_rate": 3.3, "win_rate": 50.0, "ban_rate": 0.0, "kda": 2.09, "top_items": [6676, 6697], "context_builds": {}}, {"name": "Yunara", "count": 2, "pick_rate": 3.3, "win_rate": 50.0, "ban_rate": 0.0, "kda": 2.75, "top_items": [2523, 3085, 6672], "context_builds": {}}, {"name": "Vladimir", "count": 1, "pick_rate": 1.7, "win_rate": 0.0, "ban_rate": 11.7, "kda": 0.5, "top_items": [], "context_builds": {}}, {"name": "Nilah", "count": 1, "pick_rate": 1.7, "win_rate": 0.0, "ban_rate": 0.0, "kda": 0.6, "top_items": [3036, 6676], "context_builds": {}}], "UTILITY": [{"name": "Camille", "count": 8, "pick_rate": 13.3, "win_rate": 37.5, "ban_rate": 21.7, "kda": 2.59, "top_items": [3047, 3053, 6610], "context_builds": {}}, {"name": "Pyke", "count": 5, "pick_rate": 8.3, "win_rate": 100.0, "ban_rate": 41.7, "kda": 2.73, "top_items": [3110, 3179, 3814], "context_builds": {"Tank Heavy": {"games": 3, "items": [3009, 3179, 6699]}}}, {"name": "Leona", "count": 4, "pick_rate": 6.7, "win_rate": 50.0, "ban_rate": 1.7, "kda": 1.82, "top_items": [3050, 3111], "context_builds": {}}, {"name": "Thresh", "count": 3, "pick_rate": 5.0, "win_rate": 33.3, "ban_rate": 3.3, "kda": 2.82, "top_items": [3158, 3190], "context_builds": {}}, {"name": "Seraphine", "count": 3, "pick_rate": 5.0, "win_rate": 66.7, "ban_rate": 1.7, "kda": 3.59, "top_items": [3116, 3158, 6620], "context_builds": {}}, {"name": "Senna", "count": 3, "pick_rate": 5.0, "win_rate": 33.3, "ban_rate": 10.0, "kda": 2.0, "top_items": [3009, 3071], "context_builds": {}}, {"name": "Karma", "count": 3, "pick_rate": 5.0, "win_rate": 66.7, "ban_rate": 3.3, "kda": 4.07, "top_items": [3158, 6617], "context_builds": {}}, {"name": "Alistar", "count": 3, "pick_rate": 5.0, "win_rate": 100.0, "ban_rate": 11.7, "kda": 6.0, "top_items": [3050, 3158], "context_builds": {}}, {"name": "Elise", "count": 2, "pick_rate": 3.3, "win_rate": 50.0, "ban_rate": 1.7, "kda": 2.5, "top_items": [3020, 4646], "context_builds": {}}, {"name": "Soraka", "count": 2, "pick_rate": 3.3, "win_rate": 50.0, "ban_rate": 1.7, "kda": 3.0, "top_items": [3107, 3158, 6617], "context_builds": {}}, {"name": "Nautilus", "count": 2, "pick_rate": 3.3, "win_rate": 0.0, "ban_rate": 11.7, "kda": 0.89, "top_items": [3111, 3190], "context_builds": {}}, {"name": "Nami", "count": 2, "pick_rate": 3.3, "win_rate": 100.0, "ban_rate": 0.0, "kda": 7.4, "top_items": [3107, 3222, 6620], "context_builds": {}}, {"name": "Bard", "count": 2, "pick_rate": 3.3, "win_rate": 50.0, "ban_rate": 28.3, "kda": 2.14, "top_items": [3047, 3190, 3742], "context_builds": {}}, {"name": "Neeko", "count": 1, "pick_rate": 1.7, "win_rate": 100.0, "ban_rate": 0.0, "kda": 3.33, "top_items": [3152, 3158], "context_builds": {}}, {"name": "Blitzcrank", "count": 1, "pick_rate": 1.7, "win_rate": 100.0, "ban_rate": 1.7, "kda": 11.0, "top_items": [3009, 3050, 3190], "context_builds": {}}]}}, "leaderboards": {"TOP:Gangplank": [{"player": "\ud0dc\uc591\ubb3c\uace0\uae30#6797", "region": "kr", "games": 2, "win_rate": 0.0, "kda": 1.65}, {"player": "Astra#KR4", "region": "kr", "games": 1, "win_rate": 100.0, "kda": 3.4}], "TOP:Garen": [{"player": "THEEEKIIING#KING", "region": "euw1", "games": 1, "win_rate": 100.0, "kda": 0.9}, {"player": "GABUNGKING#\uc544\uc774\uc5b4", "region": "kr", "games": 1, "win_rate": 0.0, "kda": 1.6}], "TOP:Swain": [{"player": "PerfecT#132", "region": "kr", "games": 2, "win_rate": 50.0, "kda": 1.83}], "TOP:Ambessa": [{"player": "chen#zypp", "region": "kr", "games": 1, "win_rate": 100.0, "kda": 7.5}, {"player": "Shieda Saeeun1#KAYN", "region": "euw1", "games": 1, "win_rate": 100.0, "kda": 5.0}, {"player": "SMRADOCH ROBO#EUW", "region": "euw1", "games": 1, "win_rate": 100.0, "kda": 5.0}, {"player": "elefanto#VIGIL", "region": "euw1", "games": 1, "win_rate": 100.0, "kda": 7.0}, {"player": "Caucha#148", "region": "euw1", "games": 1, "win_rate": 100.0, "kda": 6.0}, {"player": "1Jiang#7777", "region": "kr", "games": 1, "win_rate": 0.0, "kda": 1.5}, {"player": "\uc774\uc9c1\ub85c\uadf8#0904", "region": "kr", "games": 1, "win_rate": 0.0, "kda": 1.0}, {"player": "T1 Midir#KR06", "region": "kr", "games": 1, "win_rate": 0.0, "kda": 1.5}, {"player": "Corvus#DQ9", "region": "euw1", "games": 1, "win_rate": 0.0, "kda": 0.89}], "TOP:DrMundo": [{"player": "DNS Soft#2008", "region": "kr", "games": 1, "win_rate": 100.0, "kda": 7.0}, {"player": "J1U4#kr11", "region": "kr", "games": 1, "win_rate": 100.0, "kda": 1.33}, {"player": "songman#KR11", "region": "kr", "games": 1, "win_rate": 100.0, "kda": 4.5}, {"player": "MVKE Sofm#2244", "region": "kr", "games": 1, "win_rate": 0.0, "kda": 1.83}, {"player": "LiangChen#0611", "region": "kr", "games": 1, "win_rate": 0.0, "kda": 0.67}], "TOP:Jayce": [{"player": "beb14#9070", "region": "kr", "games": 1, "win_rate": 100.0, "kda": 4.5}, {"player": "xiaolanqiao#227", "region": "kr", "games": 1, "win_rate": 100.0, "kda": 3.25}, {"player": "T1 Midir#KR06", "region": "kr", "games": 1, "win_rate": 100.0, "kda": 1.25}, {"player": "karakoram2727#V8x3", "region": "euw1", "games": 1, "win_rate": 100.0, "kda": 12.0}, {"player": "Kozi#UCAM", "region": "euw1", "games": 1, "win_rate": 100.0, "kda": 4.67}, {"player": "Brrou Swain#EUW", "region": "euw1", "games": 1, "win_rate": 100.0, "kda": 2.33}, {"player": "Kingslayer#world", "region": "euw1", "games": 1, "win_rate": 100.0, "kda": 3.0}, {"player": "eeZaZ#333", "region": "euw1", "games": 1, "win_rate": 100.0, "kda": 11.67}, {"player": "\ub530\ubd09 \ub78c\uba38\uc2a4#KR1", "region": "kr", "games": 1, "win_rate": 0.0, "kda": 0.5}, {"player": "1Jiang#2003", "region": "kr", "games": 1, "win_rate": 0.0, "kda": 2.25}, {"player": "washed \u00fap#bambi", "region": "euw1", "games": 1, "win_rate": 0.0, "kda": 0.88}, {"player": "cadianNN#EUW", "region": "euw1", "games": 1, "win_rate": 0.0, "kda": 1.0}, {"player": "detdert mid acc#RANK1", "region": "euw1", "games": 1, "win_rate": 0.0, "kda": 1.38}], "TOP:Zaahen": [{"player": "\u56f4\u7ed5\u6211\u6253#05top", "region": "kr", "games": 1, "win_rate": 0.0, "kda": 0.5}], "TOP:Rumble": [{"player": "\ud574 \ud0dc#T 1", "region": "kr", "games": 2, "win_rate": 50.0, "kda": 3.12}, {"player": "Casting#KR11", "region": "kr", "games": 1, "win_rate": 100.0, "kda": 1.1}, {"player": "14\u5c0f\u5b69\u5e7b\u60f3\u8d62\u5bf9\u7ebf#4453", "region": "kr", "games": 1, "win_rate": 0.0, "kda": 0.6}], "TOP:Cassiopeia": [{"player": "\uc0b0\uba741#KR11", "region": "kr", "games": 1, "win_rate": 100.0, "kda": 1.6}, {"player": "Chang Min #KR1", "region": "kr", "games": 1, "win_rate": 100.0, "kda": 2.86}, {"player": "\u5fd7 \u61b2#\uc9c0  \ud5cc", "region": "kr", "games": 1, "win_rate": 0.0, "kda": 1.22}], "TOP:Sion": [{"player": "\ud574 \ud0dc#T 1", "region": "kr", "games": 1, "win_rate": 100.0, "kda": 14.0}], "TOP:Locke": [{"player": "1glaive#17250", "region": "euw1", "games": 1, "win_rate": 100.0, "kda": 4.67}, {"player": "\uce74\ub9ac\ub098#\uc560\uad50\uc6a9", "region": "kr", "games": 1, "win_rate": 0.0, "kda": 1.0}], "TOP:Pantheon": [{"player": "nizuizhengui#\u5c0f\u4f55\u7684\u67aa", "region": "kr", "games": 1, "win_rate": 100.0, "kda": 2.89}, {"player": "\ucc3d\uc758 \uc545\ub9c8#\uc218 \uc644", "region": "kr", "games": 1, "win_rate": 100.0, "kda": 2.17}, {"player": "Spear Shot#1111", "region": "euw1", "games": 1, "win_rate": 0.0, "kda": 1.55}], "TOP:Nidalee": [{"player": "\uc544\uc774\ub9b0#KR1", "region": "kr", "games": 1, "win_rate": 0.0, "kda": 2.0}, {"player": "\uc758\ubb38\uc758\ubc14\ub4dc\uc7a5\uc778#kr0", "region": "kr", "games": 1, "win_rate": 0.0, "kda": 0.17}], "TOP:KSante": [{"player": "sirius#6507", "region": "kr", "games": 1, "win_rate": 100.0, "kda": 1.38}, {"player": "Amel#LFT", "region": "kr", "games": 1, "win_rate": 100.0, "kda": 2.67}, {"player": "HLE \ud32c\uc11c#KR1", "region": "kr", "games": 1, "win_rate": 100.0, "kda": 13.0}, {"player": "Bean#\ucee4\ud53c\ube48", "region": "kr", "games": 1, "win_rate": 100.0, "kda": 3.67}, {"player": "Casting#KR11", "region": "kr", "games": 1, "win_rate": 100.0, "kda": 14.0}, {"player": "Ashley Kutcher#Zuhy", "region": "euw1", "games": 1, "win_rate": 100.0, "kda": 3.67}, {"player": "\ud3b8\ubbfc\uae30#\ud3b8\ubbfc\uae30", "region": "kr", "games": 1, "win_rate": 0.0, "kda": 0.25}, {"player": "LukaGaming Kille#EUW", "region": "euw1", "games": 1, "win_rate": 0.0, "kda": 0.5}], "TOP:Vayne": [{"player": "Brandnew#stric", "region": "kr", "games": 1, "win_rate": 100.0, "kda": 0.0}, {"player": "bai se zh1 chuan#qwe1", "region": "kr", "games": 1, "win_rate": 0.0, "kda": 0.83}, {"player": "\uc874\uc7ac\ud558\uc9c0 \uc54a\ub294 \uafc8#end", "region": "euw1", "games": 1, "win_rate": 0.0, "kda": 0.5}, {"player": "ZYB gen4#KR01", "region": "euw1", "games": 1, "win_rate": 0.0, "kda": 0.75}, {"player": "TwTv LadicusVibe#Vayne", "region": "euw1", "games": 1, "win_rate": 0.0, "kda": 1.69}, {"player": "Awful Things#Koala", "region": "euw1", "games": 1, "win_rate": 0.0, "kda": 0.5}], "TOP:Jax": [{"player": "\u6296\u97f3PandaC#PANDA", "region": "kr", "games": 1, "win_rate": 100.0, "kda": 1.78}, {"player": "\u5929\u4e0b\u6b66\u529f \u552f\u5feb\u4e0d\u7834#kr11", "region": "kr", "games": 1, "win_rate": 100.0, "kda": 0.5}, {"player": "T1 Midir#KR06", "region": "kr", "games": 1, "win_rate": 0.0, "kda": 1.2}, {"player": "JaxKing#FuHan", "region": "kr", "games": 1, "win_rate": 0.0, "kda": 0.6}, {"player": "\uc5b4\uca4c\ub77c\uace0\ub9de\uc9f1\ub730\uae4c#HOYA", "region": "kr", "games": 1, "win_rate": 0.0, "kda": 1.67}], "TOP:Kennen": [{"player": "tmhrnjh#1002", "region": "kr", "games": 1, "win_rate": 0.0, "kda": 1.0}], "TOP:Varus": [{"player": "Frog#KRX", "region": "kr", "games": 1, "win_rate": 100.0, "kda": 2.14}, {"player": "Relative#00003", "region": "euw1", "games": 1, "win_rate": 100.0, "kda": 8.0}, {"player": "Creepano#gfghs", "region": "euw1", "games": 1, "win_rate": 0.0, "kda": 0.11}], "TOP:Gnar": [{"player": "Pure Imagination#ZZZZZ", "region": "kr", "games": 1, "win_rate": 100.0, "kda": 0.5}, {"player": "Sharvel#1102", "region": "kr", "games": 1, "win_rate": 0.0, "kda": 1.33}], "TOP:Anivia": [{"player": "\uba54\ub871 \uc57d\uc624\ub974\uc9c0\ub871#KR2", "region": "kr", "games": 1, "win_rate": 0.0, "kda": 1.78}], "TOP:Olaf": [{"player": "\uc5b4\uca4c\ub77c\uace0\ub9de\uc9f1\ub730\uae4c#HOYA", "region": "kr", "games": 1, "win_rate": 100.0, "kda": 1.0}, {"player": "DOSEMECI NightyN#2222", "region": "euw1", "games": 1, "win_rate": 100.0, "kda": 6.0}], "TOP:Yone": [{"player": "Hyperion#0200", "region": "euw1", "games": 2, "win_rate": 100.0, "kda": 3.73}, {"player": "\u7a33\u5f53\u4eba#\u5916\u5356\u5458", "region": "kr", "games": 1, "win_rate": 0.0, "kda": 0.0}], "TOP:Yorick": [{"player": "HLE \ud32c\uc11c#KR1", "region": "kr", "games": 1, "win_rate": 0.0, "kda": 1.6}], "TOP:Aatrox": [{"player": "jackeybeibei#0810", "region": "kr", "games": 1, "win_rate": 0.0, "kda": 1.67}], "TOP:Kled": [{"player": "\uadfc\uac70\ub9ac\ud0d1\ucc54\ud504\ub9cc\ud568#\uc18d\uc558\uc9c0", "region": "kr", "games": 1, "win_rate": 0.0, "kda": 1.18}], "TOP:Shen": [{"player": "\ub543\uc950 \ub9f9\uc544\uc774#OwO", "region": "kr", "games": 1, "win_rate": 0.0, "kda": 1.5}], "TOP:Aurora": [{"player": "Rendezvous#AURI", "region": "euw1", "games": 1, "win_rate": 100.0, "kda": 1.8}, {"player": "war is eternal#5636", "region": "euw1", "games": 1, "win_rate": 100.0, "kda": 1.0}, {"player": "undersea light#KAI", "region": "euw1", "games": 1, "win_rate": 100.0, "kda": 2.17}, {"player": "\uc544 \ub728#abc", "region": "kr", "games": 1, "win_rate": 0.0, "kda": 2.0}], "TOP:Ryze": [{"player": "clkvjfkghdsfjkil#6089", "region": "kr", "games": 1, "win_rate": 100.0, "kda": 5.0}], "TOP:Mordekaiser": [{"player": "\ubc31\ud654\uc694\ub791#KR1", "region": "kr", "games": 1, "win_rate": 100.0, "kda": 0.85}], "TOP:Renekton": [{"player": "\u4e4c\u9c81\u6728\u9f50\u4e2d\u8def#Where", "region": "kr", "games": 1, "win_rate": 0.0, "kda": 0.4}, {"player": "\u96ef\u96ef\u96ef#7459", "region": "euw1", "games": 1, "win_rate": 0.0, "kda": 1.0}, {"player": "detdert jg acc#RANK1", "region": "euw1", "games": 1, "win_rate": 0.0, "kda": 0.0}], "JUNGLE:Aatrox": [{"player": "Call me Izo#igi", "region": "euw1", "games": 1, "win_rate": 100.0, "kda": 3.83}, {"player": "\uc5bc\ud130\ub108\ud2f0\ube0c#333", "region": "kr", "games": 1, "win_rate": 0.0, "kda": 2.43}, {"player": "Dreilix#CN3", "region": "euw1", "games": 1, "win_rate": 0.0, "kda": 2.5}], "JUNGLE:Zac": [{"player": "\ub7ec\ube0c \uaf49#KO1", "region": "kr", "games": 1, "win_rate": 0.0, "kda": 7.5}], "JUNGLE:Qiyana": [{"player": "legacy#0206", "region": "euw1", "games": 2, "win_rate": 0.0, "kda": 2.67}, {"player": "So be it#last", "region": "kr", "games": 1, "win_rate": 100.0, "kda": 6.0}, {"player": "\uc88b\uc544\uc694#66666", "region": "kr", "games": 1, "win_rate": 100.0, "kda": 2.71}, {"player": "Raptor#KR123", "region": "kr", "games": 1, "win_rate": 100.0, "kda": 1.0}, {"player": "eye#qy54", "region": "euw1", "games": 1, "win_rate": 100.0, "kda": 17.0}, {"player": "DNS \ub610\uc774\ube0c#KR13", "region": "kr", "games": 1, "win_rate": 0.0, "kda": 4.6}, {"player": "\uad00 \ubaa8#KR2", "region": "kr", "games": 1, "win_rate": 0.0, "kda": 4.0}], "JUNGLE:Hecarim": [{"player": "\uc774\uacf3\uc5d0 \ub0a8\uc544\uc788\uc744\uac8c#\uc5b8\uc81c\uae4c\uc9c0\ub098", "region": "kr", "games": 2, "win_rate": 100.0, "kda": 6.4}, {"player": "\uc774 \ucc28\uac00 \uc2dd\uae30\uc804\uc5d0#KR1", "region": "kr", "games": 2, "win_rate": 0.0, "kda": 2.0}, {"player": "Raptor#KR123", "region": "kr", "games": 1, "win_rate": 0.0, "kda": 4.33}, {"player": "Lapishorcux#EUW", "region": "euw1", "games": 1, "win_rate": 0.0, "kda": 3.2}, {"player": "how to get gf#solo", "region": "euw1", "games": 1, "win_rate": 0.0, "kda": 1.5}, {"player": "Oguri Cap#EUWW", "region": "euw1", "games": 1, "win_rate": 0.0, "kda": 1.43}], "JUNGLE:Naafiri": [{"player": "DNS Pyosik#KR2", "region": "kr", "games": 1, "win_rate": 100.0, "kda": 15.0}, {"player": "Juhana#OMG", "region": "kr", "games": 1, "win_rate": 100.0, "kda": 11.0}, {"player": "re0#2007", "region": "kr", "games": 1, "win_rate": 100.0, "kda": 4.75}, {"player": "Shylie#KR1", "region": "kr", "games": 1, "win_rate": 0.0, "kda": 2.6}, {"player": "legacy#0206", "region": "euw1", "games": 1, "win_rate": 0.0, "kda": 1.0}, {"player": "Mirrai#025", "region": "euw1", "games": 1, "win_rate": 0.0, "kda": 2.5}], "JUNGLE:JarvanIV": [{"player": "EMPEROR AGURIN#ROYAL", "region": "euw1", "games": 1, "win_rate": 100.0, "kda": 12.0}, {"player": "Annie IRL#Annie", "region": "euw1", "games": 1, "win_rate": 100.0, "kda": 8.0}, {"player": "ComeBack#lm27", "region": "kr", "games": 1, "win_rate": 0.0, "kda": 1.71}, {"player": "\ub77c\ucfe499#KR1", "region": "kr", "games": 1, "win_rate": 0.0, "kda": 1.62}, {"player": "\u6296\u97f3\u4e36\u5c0f\u732a\u4ed4#\u5c0f\u732a\u4ed4", "region": "kr", "games": 1, "win_rate": 0.0, "kda": 1.0}, {"player": "Kingen#KR1", "region": "kr", "games": 1, "win_rate": 0.0, "kda": 2.0}, {"player": "Scen4rio\u6f22\u9808#mid01", "region": "euw1", "games": 1, "win_rate": 0.0, "kda": 1.7}], "JUNGLE:MasterYi": [{"player": "\uc2e4\ud06c\uc1a1#\ud560\ub85c\ud560\ub85c", "region": "kr", "games": 1, "win_rate": 0.0, "kda": 1.0}, {"player": "\uc790\ud504\ud0a4\uc5d8#KR1", "region": "kr", "games": 1, "win_rate": 0.0, "kda": 0.2}], "JUNGLE:Ambessa": [{"player": "\ubb34\uac10\uc815\uc194\ub7ad\uae30\uacc4#2007", "region": "kr", "games": 1, "win_rate": 100.0, "kda": 2.5}, {"player": "DOSEMECI NightyN#2222", "region": "euw1", "games": 1, "win_rate": 100.0, "kda": 8.5}], "JUNGLE:Talon": [{"player": "GENERAL detdert#R1GX", "region": "euw1", "games": 2, "win_rate": 50.0, "kda": 2.08}, {"player": "Karasu#333", "region": "kr", "games": 1, "win_rate": 0.0, "kda": 3.67}], "JUNGLE:LeeSin": [{"player": "\uc0ac\ub791\ud569\ub2c8\ub2e4#K T", "region": "kr", "games": 1, "win_rate": 100.0, "kda": 2.86}, {"player": "Zephyr#O1O8", "region": "kr", "games": 1, "win_rate": 100.0, "kda": 20.0}, {"player": "Raptor#KR123", "region": "kr", "games": 1, "win_rate": 100.0, "kda": 6.67}, {"player": "Tweek#opzz", "region": "euw1", "games": 1, "win_rate": 100.0, "kda": 9.0}, {"player": "Rhilech#15105", "region": "euw1", "games": 1, "win_rate": 100.0, "kda": 10.0}, {"player": "\uce74\ub9ac\ub098#\uc560\uad50\uc6a9", "region": "kr", "games": 1, "win_rate": 0.0, "kda": 3.83}, {"player": "NS Ark#Lost", "region": "kr", "games": 1, "win_rate": 0.0, "kda": 0.86}, {"player": "Sharvel#1102", "region": "kr", "games": 1, "win_rate": 0.0, "kda": 1.5}, {"player": "YONG2#6666", "region": "kr", "games": 1, "win_rate": 0.0, "kda": 7.0}, {"player": "Swamp#0916", "region": "kr", "games": 1, "win_rate": 0.0, "kda": 0.5}, {"player": "\ub3fc\uc9c0\ubc14#\ub3fc\uc9c0\ube75", "region": "kr", "games": 1, "win_rate": 0.0, "kda": 0.71}, {"player": "Pungyeon#0116", "region": "kr", "games": 1, "win_rate": 0.0, "kda": 1.0}, {"player": "\uac15\uc544\uc9c0\uc88b\uc544#KR3", "region": "kr", "games": 1, "win_rate": 0.0, "kda": 2.44}], "JUNGLE:Karthus": [{"player": "Dipsy#1025", "region": "kr", "games": 1, "win_rate": 100.0, "kda": 3.5}, {"player": "solitude#0 0 0", "region": "euw1", "games": 1, "win_rate": 100.0, "kda": 3.0}], "JUNGLE:Nocturne": [{"player": "Karasu#333", "region": "kr", "games": 1, "win_rate": 100.0, "kda": 2.1}, {"player": "JDS 2115#EUW", "region": "euw1", "games": 1, "win_rate": 100.0, "kda": 6.0}, {"player": "\uc774\uacf3\uc5d0 \ub0a8\uc544\uc788\uc744\uac8c#\uc5b8\uc81c\uae4c\uc9c0\ub098", "region": "kr", "games": 1, "win_rate": 0.0, "kda": 1.33}, {"player": "Monkebrain#4922", "region": "euw1", "games": 1, "win_rate": 0.0, "kda": 2.22}], "JUNGLE:Kayn": [{"player": "Natalie#0304", "region": "kr", "games": 1, "win_rate": 100.0, "kda": 4.33}, {"player": "\u534e\u4e3a\u4e2d\u5355#ltz", "region": "kr", "games": 1, "win_rate": 100.0, "kda": 1.73}], "JUNGLE:Elise": [{"player": "zzzzzzcry#0520", "region": "kr", "games": 1, "win_rate": 100.0, "kda": 19.0}, {"player": "XiXi#716", "region": "kr", "games": 1, "win_rate": 0.0, "kda": 1.6}], "JUNGLE:Viego": [{"player": "KRX Vincenzo#KR4", "region": "kr", "games": 1, "win_rate": 100.0, "kda": 7.33}, {"player": "who is remnant#nenad", "region": "euw1", "games": 1, "win_rate": 100.0, "kda": 3.0}, {"player": "Gala\u021bi#77251", "region": "euw1", "games": 1, "win_rate": 100.0, "kda": 2.5}, {"player": "UREK MAZINO#ZTMY", "region": "euw1", "games": 1, "win_rate": 0.0, "kda": 2.0}, {"player": "legacy#0206", "region": "euw1", "games": 1, "win_rate": 0.0, "kda": 2.43}], "JUNGLE:XinZhao": [{"player": "xiaocaobao#\ub2c8\uc5bc\uade4", "region": "kr", "games": 1, "win_rate": 0.0, "kda": 0.67}], "JUNGLE:Vi": [{"player": "Swamp#0916", "region": "kr", "games": 2, "win_rate": 0.0, "kda": 2.79}, {"player": "DNS Pyosik#KR2", "region": "kr", "games": 1, "win_rate": 0.0, "kda": 2.57}, {"player": "\u57ce\u90ca\u7267\u7b1b\u58f0#0404", "region": "euw1", "games": 1, "win_rate": 0.0, "kda": 1.14}], "JUNGLE:Kindred": [{"player": "dy\u7070\u767d\u9b3c\u602a#\u8def\u8fc7\u4eba\u95f4", "region": "kr", "games": 1, "win_rate": 100.0, "kda": 2.0}, {"player": "\uc601 \uc7ac#KR111", "region": "kr", "games": 1, "win_rate": 100.0, "kda": 14.0}, {"player": "ttv ronaldoo#1234", "region": "euw1", "games": 1, "win_rate": 0.0, "kda": 1.33}], "JUNGLE:Skarner": [{"player": "\u6296\u97f3PandaC#PANDA", "region": "kr", "games": 1, "win_rate": 100.0, "kda": 7.5}, {"player": "MadScientist#TTV", "region": "euw1", "games": 1, "win_rate": 0.0, "kda": 3.0}], "JUNGLE:Sylas": [{"player": "OnPi#\uc628 \ud53c", "region": "kr", "games": 1, "win_rate": 100.0, "kda": 6.5}, {"player": "Rhilech#15105", "region": "euw1", "games": 1, "win_rate": 100.0, "kda": 7.67}], "JUNGLE:Belveth": [{"player": "\u6296\u97f3\u79cb\u5bd2#Kr99", "region": "kr", "games": 2, "win_rate": 50.0, "kda": 7.0}, {"player": "Opscurra#2025", "region": "euw1", "games": 1, "win_rate": 100.0, "kda": 6.25}, {"player": "YONG2#6666", "region": "kr", "games": 1, "win_rate": 0.0, "kda": 1.8}], "JUNGLE:Olaf": [{"player": "burning#KR7", "region": "kr", "games": 1, "win_rate": 100.0, "kda": 7.25}, {"player": "DOSEMECI NightyN#2222", "region": "euw1", "games": 1, "win_rate": 100.0, "kda": 5.67}], "JUNGLE:Jayce": [{"player": "\uad00 \ubaa8#KR2", "region": "kr", "games": 1, "win_rate": 0.0, "kda": 2.0}], "JUNGLE:Nidalee": [{"player": "\u6853\u6211\u547d\u6765#\u6853\u6853\u63a7", "region": "kr", "games": 1, "win_rate": 100.0, "kda": 7.5}, {"player": "G O#123", "region": "kr", "games": 1, "win_rate": 100.0, "kda": 4.11}, {"player": "Tweek#opzz", "region": "euw1", "games": 1, "win_rate": 100.0, "kda": 5.0}], "JUNGLE:Locke": [{"player": "\ub3fc\uc9c0\ubc14#\ub3fc\uc9c0\ube75", "region": "kr", "games": 1, "win_rate": 100.0, "kda": 6.67}, {"player": "Karasu#333", "region": "kr", "games": 1, "win_rate": 0.0, "kda": 2.2}, {"player": "\uff82 \uff82 \uff82 \uff82 \uff82 \uff82 \uff82 \uff82#10231", "region": "euw1", "games": 1, "win_rate": 0.0, "kda": 1.71}], "JUNGLE:Zyra": [{"player": "guz1vjppr0kut3#2810", "region": "kr", "games": 1, "win_rate": 100.0, "kda": 0.0}], "JUNGLE:Trundle": [{"player": "DNS \ub610\uc774\ube0c#KR13", "region": "kr", "games": 1, "win_rate": 100.0, "kda": 23.0}], "MIDDLE:Sylas": [{"player": "\ucd5c\uc6b0\uc81c#\uc18c\ub9ac\uafbc", "region": "euw1", "games": 1, "win_rate": 100.0, "kda": 5.75}, {"player": "ttv ronaldoo#1234", "region": "euw1", "games": 1, "win_rate": 100.0, "kda": 7.0}, {"player": "bench 115kg ez#gym", "region": "euw1", "games": 1, "win_rate": 100.0, "kda": 3.67}, {"player": "\uc548\ub155 \uc2dc\uac04\uc758 \uc232#LOL", "region": "kr", "games": 1, "win_rate": 0.0, "kda": 1.45}, {"player": "\ub0a0\uc544\ub77c#0115", "region": "kr", "games": 1, "win_rate": 0.0, "kda": 2.83}, {"player": "OnPi#\uc628 \ud53c", "region": "kr", "games": 1, "win_rate": 0.0, "kda": 1.88}], "MIDDLE:Viktor": [{"player": "\uae38\uac00\ub2e4\uac00\uae4c\uae4c\uc0ac\ub2ec\ub77c\uace0\uc870\ub974\ub294\uc774\ub3c4\uc724#KR1", "region": "kr", "games": 1, "win_rate": 0.0, "kda": 0.57}], "MIDDLE:Vladimir": [{"player": "89ok1#Miss", "region": "kr", "games": 1, "win_rate": 0.0, "kda": 1.58}], "MIDDLE:Azir": [{"player": "xiaocaobao#\ub2c8\uc5bc\uade4", "region": "kr", "games": 1, "win_rate": 100.0, "kda": 4.0}], "MIDDLE:Xerath": [{"player": "\ud0d5 \uad6d#S T", "region": "kr", "games": 1, "win_rate": 0.0, "kda": 3.0}], "MIDDLE:Akshan": [{"player": "xinyanbajian#KR1", "region": "kr", "games": 1, "win_rate": 100.0, "kda": 0.0}, {"player": "\u7a33\u5f53\u4eba#\u5916\u5356\u5458", "region": "kr", "games": 1, "win_rate": 0.0, "kda": 0.91}], "MIDDLE:Cassiopeia": [{"player": "babykiki#KR1", "region": "kr", "games": 1, "win_rate": 100.0, "kda": 1.5}, {"player": "srysrymb#1065", "region": "kr", "games": 1, "win_rate": 100.0, "kda": 6.5}, {"player": "\ubcbc\ub77d\uc2dd\ud61c#0070", "region": "kr", "games": 1, "win_rate": 100.0, "kda": 0.82}, {"player": "qeqweasf#asdf", "region": "euw1", "games": 1, "win_rate": 100.0, "kda": 0.93}, {"player": "\uc2e0\ub09c \ub9dd\uace0#0417", "region": "kr", "games": 1, "win_rate": 0.0, "kda": 1.33}, {"player": "\u4e2d\u8def\u9738\u4e3b#MID", "region": "euw1", "games": 1, "win_rate": 0.0, "kda": 1.0}], "MIDDLE:Ryze": [{"player": "livinli#KR1", "region": "kr", "games": 1, "win_rate": 100.0, "kda": 2.5}, {"player": "Pungyeon#0116", "region": "kr", "games": 1, "win_rate": 0.0, "kda": 0.5}], "MIDDLE:Orianna": [{"player": "livinli#KR1", "region": "kr", "games": 2, "win_rate": 0.0, "kda": 1.38}, {"player": "\ub3c4\ucc9c\uc9c0#KR1", "region": "kr", "games": 1, "win_rate": 100.0, "kda": 2.67}, {"player": "DizL#2297", "region": "euw1", "games": 1, "win_rate": 100.0, "kda": 2.0}, {"player": "Pungyeon#0116", "region": "kr", "games": 1, "win_rate": 0.0, "kda": 2.75}, {"player": "Frog#KRX", "region": "kr", "games": 1, "win_rate": 0.0, "kda": 2.75}], "MIDDLE:Nocturne": [{"player": "gushouyu#zypp", "region": "kr", "games": 1, "win_rate": 100.0, "kda": 2.43}], "MIDDLE:Zoe": [{"player": "Holder#kr2", "region": "kr", "games": 1, "win_rate": 100.0, "kda": 28.0}, {"player": "Witt#123", "region": "kr", "games": 1, "win_rate": 0.0, "kda": 2.71}, {"player": "\ud558\uc728\uc774 \ub0a8\ud3b8#evee", "region": "kr", "games": 1, "win_rate": 0.0, "kda": 9.0}], "MIDDLE:Locke": [{"player": "Mr useful#361", "region": "euw1", "games": 2, "win_rate": 50.0, "kda": 2.47}, {"player": "\u97d3\u5929\u5c0a#AZIRK", "region": "kr", "games": 1, "win_rate": 100.0, "kda": 2.43}, {"player": "Yuny#\uc720\ub2c8\uc9dc\uc7a5\ub9e8", "region": "kr", "games": 1, "win_rate": 100.0, "kda": 8.67}, {"player": "\uad6c\ub984\ub2e4\ub9ac\ub18d\uc7a5#0120", "region": "kr", "games": 1, "win_rate": 100.0, "kda": 5.5}, {"player": "Abbedagg\u00c6#EUW", "region": "euw1", "games": 1, "win_rate": 100.0, "kda": 4.33}, {"player": "SeRiN1#EUW", "region": "euw1", "games": 1, "win_rate": 100.0, "kda": 4.75}, {"player": "Maldives#0727", "region": "kr", "games": 1, "win_rate": 0.0, "kda": 4.6}, {"player": "KRX AKaJe#MUR", "region": "kr", "games": 1, "win_rate": 0.0, "kda": 1.33}, {"player": "ttv ronaldoo#1234", "region": "euw1", "games": 1, "win_rate": 0.0, "kda": 1.86}, {"player": "RRRR IX#Majin", "region": "euw1", "games": 1, "win_rate": 0.0, "kda": 2.43}, {"player": "Gala\u021bi#77251", "region": "euw1", "games": 1, "win_rate": 0.0, "kda": 3.57}], "MIDDLE:Yone": [{"player": "olives cheese#pasta", "region": "euw1", "games": 3, "win_rate": 33.3, "kda": 1.68}, {"player": "\uc0b0\uba741#KR11", "region": "kr", "games": 1, "win_rate": 100.0, "kda": 14.0}, {"player": "\u534e\u4e3a\u4e2d\u5355#ltz", "region": "kr", "games": 1, "win_rate": 100.0, "kda": 2.6}, {"player": "Schmuseyone#BZZ", "region": "euw1", "games": 1, "win_rate": 100.0, "kda": 7.33}, {"player": "EPG \uce74\uc774\uc870\ucfe0\ub2e8#\uc870 \ub85c", "region": "kr", "games": 1, "win_rate": 0.0, "kda": 0.33}, {"player": "KRX AKaJe#MUR", "region": "kr", "games": 1, "win_rate": 0.0, "kda": 2.25}, {"player": "Menaceson#Tanja", "region": "euw1", "games": 1, "win_rate": 0.0, "kda": 0.38}], "MIDDLE:Yasuo": [{"player": "KC Kamiloo#FIRE", "region": "euw1", "games": 1, "win_rate": 100.0, "kda": 2.5}, {"player": "Lets \u6545#AMIN", "region": "kr", "games": 1, "win_rate": 0.0, "kda": 1.8}, {"player": "Crow#crow9", "region": "kr", "games": 1, "win_rate": 0.0, "kda": 1.22}, {"player": "\uc2e0\ub09c \ub9dd\uace0#0417", "region": "kr", "games": 1, "win_rate": 0.0, "kda": 0.0}], "MIDDLE:Lissandra": [{"player": "\uc800\uc2a4\ud2f4 \uac8c\uc774\uce58#7804", "region": "kr", "games": 1, "win_rate": 100.0, "kda": 2.43}], "MIDDLE:Hwei": [{"player": "TWTV Peng04#Yuqi", "region": "euw1", "games": 1, "win_rate": 100.0, "kda": 3.0}, {"player": "RED#Mio\u97e9\u670d", "region": "kr", "games": 1, "win_rate": 0.0, "kda": 0.4}], "MIDDLE:DrMundo": [{"player": "WBG\u62db641950117#WBG", "region": "kr", "games": 1, "win_rate": 100.0, "kda": 2.75}], "MIDDLE:Ekko": [{"player": "Twitch Six10lol#Six7", "region": "euw1", "games": 2, "win_rate": 100.0, "kda": 10.0}, {"player": "Unique#0303", "region": "kr", "games": 1, "win_rate": 100.0, "kda": 4.0}], "MIDDLE:Diana": [{"player": "ice seven zero#0721", "region": "kr", "games": 1, "win_rate": 0.0, "kda": 1.75}], "MIDDLE:TwistedFate": [{"player": "ttv ronaldoo#1234", "region": "euw1", "games": 1, "win_rate": 100.0, "kda": 4.4}, {"player": "Annie IRL#Annie", "region": "euw1", "games": 1, "win_rate": 100.0, "kda": 4.5}, {"player": "ice seven zero#0721", "region": "kr", "games": 1, "win_rate": 0.0, "kda": 0.33}, {"player": "xiaocaobao#\ub2c8\uc5bc\uade4", "region": "kr", "games": 1, "win_rate": 0.0, "kda": 3.33}], "MIDDLE:Syndra": [{"player": "gynang#1234", "region": "kr", "games": 1, "win_rate": 100.0, "kda": 1.0}, {"player": "Pungyeon#0116", "region": "kr", "games": 1, "win_rate": 100.0, "kda": 2.5}, {"player": "ttv ronaldoo#1234", "region": "euw1", "games": 1, "win_rate": 100.0, "kda": 4.33}, {"player": "Po Gap#EUW", "region": "euw1", "games": 1, "win_rate": 100.0, "kda": 2.6}, {"player": "Notiko#EUW01", "region": "euw1", "games": 1, "win_rate": 100.0, "kda": 5.75}, {"player": "ice seven zero#0721", "region": "kr", "games": 1, "win_rate": 0.0, "kda": 0.14}, {"player": "Twitch Six10lol#Six7", "region": "euw1", "games": 1, "win_rate": 0.0, "kda": 2.18}], "MIDDLE:Riven": [{"player": "\u4e16\u4e00\u4e0a\u5929\u7070\u7070#Riven", "region": "kr", "games": 1, "win_rate": 100.0, "kda": 14.0}], "MIDDLE:Akali": [{"player": "Pungyeon#0116", "region": "kr", "games": 2, "win_rate": 50.0, "kda": 2.93}, {"player": "SeTab#123", "region": "kr", "games": 1, "win_rate": 100.0, "kda": 5.33}, {"player": "\ucd78\ube44 \ud050 \ub3cc\ub824 #KR1", "region": "kr", "games": 1, "win_rate": 100.0, "kda": 5.0}, {"player": "\uae30\uc0ac\ud0a4#bee", "region": "kr", "games": 1, "win_rate": 0.0, "kda": 0.91}, {"player": "F\u0395DEVALVERDE8#RMA", "region": "euw1", "games": 1, "win_rate": 0.0, "kda": 2.0}, {"player": "G\u00d8DSH\u0394RD DESC\u039eNT#333", "region": "euw1", "games": 1, "win_rate": 0.0, "kda": 0.8}, {"player": "Fred#yuki", "region": "euw1", "games": 1, "win_rate": 0.0, "kda": 3.17}], "MIDDLE:Tristana": [{"player": "Faker#\uad6c\ub77c\ud2f0", "region": "kr", "games": 1, "win_rate": 100.0, "kda": 3.67}, {"player": "xiaocaobao#\ub2c8\uc5bc\uade4", "region": "kr", "games": 1, "win_rate": 100.0, "kda": 1.14}], "MIDDLE:Galio": [{"player": "lingyo#6511", "region": "kr", "games": 1, "win_rate": 100.0, "kda": 14.0}, {"player": "Tom Pearl#EUWW", "region": "euw1", "games": 1, "win_rate": 100.0, "kda": 7.67}, {"player": "ParisVan#\u4e0d\u77e5\u540d\u6b4c\u624b", "region": "kr", "games": 1, "win_rate": 0.0, "kda": 0.2}, {"player": "AM2PM#PM2AM", "region": "euw1", "games": 1, "win_rate": 0.0, "kda": 1.5}], "MIDDLE:Qiyana": [{"player": "3era#333", "region": "kr", "games": 1, "win_rate": 100.0, "kda": 2.82}, {"player": "\u5c0fy\u662f\u795e#man", "region": "kr", "games": 1, "win_rate": 0.0, "kda": 0.33}], "MIDDLE:Ahri": [{"player": "TWTV Peng04#Hanni", "region": "euw1", "games": 1, "win_rate": 100.0, "kda": 5.0}, {"player": "\ud558\uc597\uace0\uc608\uc068#KR1", "region": "kr", "games": 1, "win_rate": 0.0, "kda": 0.25}], "MIDDLE:Fiora": [{"player": "love draco#DRACO", "region": "kr", "games": 1, "win_rate": 100.0, "kda": 2.45}], "MIDDLE:Taliyah": [{"player": "gynang#1234", "region": "kr", "games": 1, "win_rate": 100.0, "kda": 6.0}, {"player": "zwaker#T1WIN", "region": "euw1", "games": 1, "win_rate": 0.0, "kda": 5.33}], "MIDDLE:Aurora": [{"player": "Rendezvous#AURI", "region": "euw1", "games": 2, "win_rate": 0.0, "kda": 0.93}, {"player": "WBG\u62db641950117#WBG", "region": "kr", "games": 1, "win_rate": 0.0, "kda": 1.6}, {"player": "Wompwomp#wub", "region": "euw1", "games": 1, "win_rate": 0.0, "kda": 3.83}], "BOTTOM:Ziggs": [{"player": "yoshi#kr4", "region": "kr", "games": 1, "win_rate": 100.0, "kda": 19.0}, {"player": "ASTAGHFIRULLAH#PLS", "region": "euw1", "games": 1, "win_rate": 100.0, "kda": 7.0}, {"player": "Creative Self#KR1", "region": "kr", "games": 1, "win_rate": 0.0, "kda": 1.36}, {"player": "\ud558 \ub2c8#1212", "region": "kr", "games": 1, "win_rate": 0.0, "kda": 0.82}, {"player": "bai se zh1 chuan#qwe1", "region": "kr", "games": 1, "win_rate": 0.0, "kda": 0.67}, {"player": "Rocks D Xebec#91919", "region": "euw1", "games": 1, "win_rate": 0.0, "kda": 4.57}, {"player": "detdert adc acc#RANK1", "region": "euw1", "games": 1, "win_rate": 0.0, "kda": 3.67}], "BOTTOM:Sivir": [{"player": "\ub178\uc775\uc2a4\uac15#noex", "region": "kr", "games": 1, "win_rate": 100.0, "kda": 2.5}, {"player": "T1 Eclipse#2009", "region": "kr", "games": 1, "win_rate": 0.0, "kda": 4.5}, {"player": "\uc9c4\uc870 \uc54c\ud018\uc774\ub4dc #KR1", "region": "kr", "games": 1, "win_rate": 0.0, "kda": 1.29}], "BOTTOM:Yunara": [{"player": "Attacking#kr2", "region": "kr", "games": 1, "win_rate": 100.0, "kda": 3.0}, {"player": "tadijfolz1em#KR1", "region": "kr", "games": 1, "win_rate": 100.0, "kda": 7.5}, {"player": "T1 Smash#2006", "region": "euw1", "games": 1, "win_rate": 100.0, "kda": 6.67}, {"player": "baekjongmin#0812", "region": "kr", "games": 1, "win_rate": 0.0, "kda": 3.0}, {"player": "Peanut#05012", "region": "kr", "games": 1, "win_rate": 0.0, "kda": 2.4}, {"player": "\ud3b8\ubbfc\uae30#\ud3b8\ubbfc\uae30", "region": "kr", "games": 1, "win_rate": 0.0, "kda": 2.12}, {"player": "\u00c9vangelyne#BELGE", "region": "euw1", "games": 1, "win_rate": 0.0, "kda": 1.44}], "BOTTOM:Cassiopeia": [{"player": "\u5fd7 \u61b2#\uc9c0  \ud5cc", "region": "kr", "games": 1, "win_rate": 100.0, "kda": 4.0}, {"player": "\ubbf8\ub4dc\uac00\ub0b4\ud604#0207", "region": "kr", "games": 1, "win_rate": 0.0, "kda": 0.17}, {"player": "xiaolongxia#3223", "region": "euw1", "games": 1, "win_rate": 0.0, "kda": 1.22}], "BOTTOM:Syndra": [{"player": "livinli#KR1", "region": "kr", "games": 1, "win_rate": 100.0, "kda": 2.0}, {"player": "\uaf2c\ub9c8\ub529\uad6c\ub9ac#KR1", "region": "kr", "games": 1, "win_rate": 100.0, "kda": 7.0}, {"player": "\ud0dc \uc724#BFX", "region": "kr", "games": 1, "win_rate": 100.0, "kda": 2.6}, {"player": "bai se zh1 chuan#qwe1", "region": "kr", "games": 1, "win_rate": 100.0, "kda": 8.0}, {"player": "\ud55c\uad6d\uc778\uc774 \uc544\ub2c8\ub2e4#EUW0", "region": "euw1", "games": 1, "win_rate": 100.0, "kda": 2.67}, {"player": "buffi#1505", "region": "euw1", "games": 1, "win_rate": 100.0, "kda": 1.75}, {"player": "Ketsuo#1386", "region": "euw1", "games": 1, "win_rate": 100.0, "kda": 6.0}, {"player": "T1 \uc5d0\ud14c\ub974#1225", "region": "kr", "games": 1, "win_rate": 0.0, "kda": 1.5}, {"player": "\ub9dd\uace0\uc9f1#8468", "region": "kr", "games": 1, "win_rate": 0.0, "kda": 1.67}, {"player": "HLE \ud32c\uc11c#KR1", "region": "kr", "games": 1, "win_rate": 0.0, "kda": 1.0}, {"player": "Cocytos#Him", "region": "euw1", "games": 1, "win_rate": 0.0, "kda": 0.83}, {"player": "G2 Hans Sama#12838", "region": "euw1", "games": 1, "win_rate": 0.0, "kda": 0.58}, {"player": "GALA RULER AEON#EUW", "region": "euw1", "games": 1, "win_rate": 0.0, "kda": 1.89}], "BOTTOM:Corki": [{"player": "me jg can carry#KR1", "region": "kr", "games": 1, "win_rate": 0.0, "kda": 1.29}], "BOTTOM:Lucian": [{"player": "Rainy day#0808", "region": "kr", "games": 1, "win_rate": 100.0, "kda": 1.75}, {"player": "bai se zh1 chuan#qwe1", "region": "kr", "games": 1, "win_rate": 100.0, "kda": 4.8}, {"player": "Seiichi Yukimura#0305", "region": "kr", "games": 1, "win_rate": 0.0, "kda": 0.83}, {"player": "Cocytos#Him", "region": "euw1", "games": 1, "win_rate": 0.0, "kda": 1.38}], "BOTTOM:Jinx": [{"player": "SCL Filou#Scald", "region": "euw1", "games": 3, "win_rate": 100.0, "kda": 3.62}, {"player": "NinjaKiwi#KoR", "region": "kr", "games": 1, "win_rate": 100.0, "kda": 2.0}], "BOTTOM:Jhin": [{"player": "\u67f3\u667a\u654f#2849", "region": "kr", "games": 1, "win_rate": 100.0, "kda": 4.5}, {"player": "joeyscags#Life", "region": "euw1", "games": 1, "win_rate": 100.0, "kda": 5.0}, {"player": "Departures#Kami", "region": "kr", "games": 1, "win_rate": 0.0, "kda": 1.6}, {"player": "addong#KR7", "region": "kr", "games": 1, "win_rate": 0.0, "kda": 1.0}, {"player": "ADINAKIGN#7339", "region": "kr", "games": 1, "win_rate": 0.0, "kda": 4.0}, {"player": "truthZZ#QAQ", "region": "kr", "games": 1, "win_rate": 0.0, "kda": 1.33}, {"player": "nihongo#sun", "region": "euw1", "games": 1, "win_rate": 0.0, "kda": 1.0}], "BOTTOM:Tristana": [{"player": "\uc655\uc655\ub9e8#\uc655\uc655\uc655", "region": "kr", "games": 1, "win_rate": 100.0, "kda": 3.83}], "BOTTOM:Sylas": [{"player": "\ubc14\ubc14\ubc14\ubc24#1999", "region": "kr", "games": 1, "win_rate": 0.0, "kda": 1.0}, {"player": "WE GO#\uc774\ub098\uacbd", "region": "kr", "games": 1, "win_rate": 0.0, "kda": 1.67}, {"player": "\ud3b8\ubbfc\uae30#\ud3b8\ubbfc\uae30", "region": "kr", "games": 1, "win_rate": 0.0, "kda": 1.43}], "BOTTOM:Ezreal": [{"player": "Lucky WhaleShark#\ud589\uace0\uc0c1", "region": "kr", "games": 1, "win_rate": 100.0, "kda": 7.67}, {"player": "cccxxx#0203", "region": "kr", "games": 1, "win_rate": 100.0, "kda": 0.0}, {"player": "Notiko#EUW01", "region": "euw1", "games": 1, "win_rate": 100.0, "kda": 0.33}, {"player": "\ud55c\uad6d\uc778\uc774 \uc544\ub2c8\ub2e4#EUW0", "region": "euw1", "games": 1, "win_rate": 100.0, "kda": 8.0}, {"player": "\u591csnowpoem#love", "region": "euw1", "games": 1, "win_rate": 100.0, "kda": 5.0}, {"player": "\u4e0d\u5403\u9999\u83dc#KR2", "region": "kr", "games": 1, "win_rate": 0.0, "kda": 0.56}, {"player": "Bonnie#0314", "region": "kr", "games": 1, "win_rate": 0.0, "kda": 2.55}, {"player": "ZYB gen4#KR01", "region": "euw1", "games": 1, "win_rate": 0.0, "kda": 2.57}, {"player": "Mdd#3113", "region": "euw1", "games": 1, "win_rate": 0.0, "kda": 2.5}, {"player": "ttv ronaldoo#1234", "region": "euw1", "games": 1, "win_rate": 0.0, "kda": 3.0}], "BOTTOM:Viktor": [{"player": "MAGEBLOOD#E500", "region": "kr", "games": 1, "win_rate": 100.0, "kda": 8.67}, {"player": "SeTab#123", "region": "kr", "games": 1, "win_rate": 100.0, "kda": 3.2}, {"player": "\u9668\u843d\u7684\u5929\u624d#\u4e16\u4e00\u4e2d\u9633\u6797", "region": "kr", "games": 1, "win_rate": 0.0, "kda": 0.75}, {"player": "Creepy Nuts#042", "region": "euw1", "games": 1, "win_rate": 0.0, "kda": 1.33}], "BOTTOM:Kaisa": [{"player": "Karis#KR4", "region": "kr", "games": 1, "win_rate": 100.0, "kda": 22.0}, {"player": "chesterbb#0811", "region": "kr", "games": 1, "win_rate": 100.0, "kda": 4.25}, {"player": "Ghost#\uc62c\ub77c\uac11\ub2c8\ub2e4", "region": "kr", "games": 1, "win_rate": 100.0, "kda": 2.38}, {"player": "\ucd5c\uc6b0\uc81c#\uc18c\ub9ac\uafbc", "region": "euw1", "games": 1, "win_rate": 100.0, "kda": 3.5}, {"player": "\uac00 \ub78c#1368", "region": "kr", "games": 1, "win_rate": 0.0, "kda": 1.9}, {"player": "LVS667#LKV4L", "region": "euw1", "games": 1, "win_rate": 0.0, "kda": 1.8}], "BOTTOM:Jayce": [{"player": "\ub3c5\uae30\ud488\uae30#123", "region": "kr", "games": 1, "win_rate": 100.0, "kda": 2.71}, {"player": "WE GO#\uc774\ub098\uacbd", "region": "kr", "games": 1, "win_rate": 0.0, "kda": 0.5}], "BOTTOM:Hwei": [{"player": "haerin#\ud558\uc774\ub9b0", "region": "kr", "games": 1, "win_rate": 100.0, "kda": 2.0}, {"player": "\ud0dc \uc724#BFX", "region": "kr", "games": 1, "win_rate": 0.0, "kda": 2.14}, {"player": "WE GO#\uc774\ub098\uacbd", "region": "kr", "games": 1, "win_rate": 0.0, "kda": 1.4}], "BOTTOM:Xerath": [{"player": "\ud2b8\ub798\ud0b9#99999", "region": "kr", "games": 1, "win_rate": 100.0, "kda": 1.33}, {"player": "eqwdqg#KR1", "region": "kr", "games": 1, "win_rate": 100.0, "kda": 2.8}, {"player": "Robin#\u661f\u671f\u65e5", "region": "kr", "games": 1, "win_rate": 0.0, "kda": 2.0}], "BOTTOM:Mel": [{"player": "\uc0ac\uc2e4\ubd10\uc900\uac70\uc57c#KR1", "region": "kr", "games": 1, "win_rate": 100.0, "kda": 7.0}, {"player": "BAR MOJITO#MACA", "region": "euw1", "games": 1, "win_rate": 100.0, "kda": 2.25}, {"player": "trymboner#2000", "region": "euw1", "games": 1, "win_rate": 100.0, "kda": 1.75}, {"player": "ttv ronaldoo#1234", "region": "euw1", "games": 1, "win_rate": 100.0, "kda": 5.67}, {"player": "OnPi#\uc628 \ud53c", "region": "kr", "games": 1, "win_rate": 0.0, "kda": 0.0}, {"player": "Gunfire#ADC3", "region": "euw1", "games": 1, "win_rate": 0.0, "kda": 1.12}], "BOTTOM:Aphelios": [{"player": "ParisVan#\u4e0d\u77e5\u540d\u6b4c\u624b", "region": "kr", "games": 1, "win_rate": 0.0, "kda": 0.89}], "BOTTOM:Ashe": [{"player": "Cannabi#1015", "region": "kr", "games": 1, "win_rate": 100.0, "kda": 2.12}, {"player": "\uc6b0\ub9ac\uc9d1\uc5d0 \ubcf4\ub7ec\uc62c\ub798#\uc544\ub098\ucf58\ub2e4", "region": "kr", "games": 1, "win_rate": 0.0, "kda": 0.0}, {"player": "bai se zh1 chuan#qwe1", "region": "kr", "games": 1, "win_rate": 0.0, "kda": 2.0}, {"player": "Clearlight#3672", "region": "euw1", "games": 1, "win_rate": 0.0, "kda": 0.86}], "BOTTOM:Ambessa": [{"player": "\ud654\ucc3d\ud55c\ub0a0\ub9d1\uc740\uad6c\ub984#\ud1a0\uadfc\uc774", "region": "kr", "games": 1, "win_rate": 100.0, "kda": 2.0}], "BOTTOM:Xayah": [{"player": "Cannabi#1015", "region": "kr", "games": 1, "win_rate": 100.0, "kda": 2.5}], "UTILITY:Pantheon": [{"player": "\u9668\u843d\u7684\u5929\u624d#\u4e16\u4e00\u4e2d\u9633\u6797", "region": "kr", "games": 1, "win_rate": 100.0, "kda": 3.5}, {"player": "\uc774\uc9c0\ub9cc\uc758\ud558\ub8e8#\uc774\uc9c0\ub9cc", "region": "kr", "games": 1, "win_rate": 100.0, "kda": 1.56}, {"player": "YoRu#KR7", "region": "kr", "games": 1, "win_rate": 0.0, "kda": 1.07}, {"player": "aqswdefrgt#777", "region": "kr", "games": 1, "win_rate": 0.0, "kda": 1.5}, {"player": "xX King Xx#GOD", "region": "kr", "games": 1, "win_rate": 0.0, "kda": 1.12}, {"player": "Darkclones#EUW", "region": "euw1", "games": 1, "win_rate": 0.0, "kda": 0.92}], "UTILITY:Camille": [{"player": "Ghost#\uc62c\ub77c\uac11\ub2c8\ub2e4", "region": "kr", "games": 2, "win_rate": 50.0, "kda": 2.4}, {"player": "Bluffing#1207", "region": "kr", "games": 2, "win_rate": 50.0, "kda": 3.5}, {"player": "KRX \uc824\ub9ac\ucd5c#KR123", "region": "kr", "games": 1, "win_rate": 100.0, "kda": 3.5}, {"player": "\ub9c8\ubc95\uacf5\ud559 \uc0c1\uc790#KR1", "region": "kr", "games": 1, "win_rate": 100.0, "kda": 1.6}, {"player": "ROSS Smarty#smt", "region": "euw1", "games": 1, "win_rate": 100.0, "kda": 7.33}, {"player": "PatkicaA#EUW", "region": "euw1", "games": 1, "win_rate": 100.0, "kda": 2.5}, {"player": "Brevitate Vitae#EUW", "region": "euw1", "games": 1, "win_rate": 100.0, "kda": 3.6}, {"player": "\u60f3\u56de\u5bb6#real", "region": "kr", "games": 1, "win_rate": 0.0, "kda": 0.92}, {"player": "Ding Liren#1992", "region": "kr", "games": 1, "win_rate": 0.0, "kda": 2.44}, {"player": "ParisVan#\u4e0d\u77e5\u540d\u6b4c\u624b", "region": "kr", "games": 1, "win_rate": 0.0, "kda": 1.2}, {"player": "Sweet Onion#1218", "region": "kr", "games": 1, "win_rate": 0.0, "kda": 0.8}, {"player": "\ubc15 \uc528#KR123", "region": "kr", "games": 1, "win_rate": 0.0, "kda": 2.17}, {"player": "sametizibabo#men", "region": "euw1", "games": 1, "win_rate": 0.0, "kda": 3.67}, {"player": "basil#fan", "region": "euw1", "games": 1, "win_rate": 0.0, "kda": 2.38}, {"player": "qeqweasf#asdf", "region": "euw1", "games": 1, "win_rate": 0.0, "kda": 1.0}, {"player": "Mr useful#361", "region": "euw1", "games": 1, "win_rate": 0.0, "kda": 2.0}, {"player": "\u017bywiec#Orzeu", "region": "euw1", "games": 1, "win_rate": 0.0, "kda": 2.83}], "UTILITY:Pyke": [{"player": "\ub0b4\ub9d0\ub4e4\ub9ac\ub2c8\uc65c\uc774\ub807\uac8c\ub9d0\ub838\uc5b4#\ucc2c\uc131\uc815", "region": "kr", "games": 1, "win_rate": 100.0, "kda": 1.14}, {"player": "\ud669\ud63c\uc6b0\uc8fc\uc790\uc57c#\ud669 \ud63c", "region": "kr", "games": 1, "win_rate": 100.0, "kda": 6.0}, {"player": "EDG BuLLDoG#KR2", "region": "kr", "games": 1, "win_rate": 100.0, "kda": 4.2}, {"player": "\u5c0f \u4e91#ziye", "region": "kr", "games": 1, "win_rate": 100.0, "kda": 0.73}, {"player": "SLENDOOOO#DAC", "region": "euw1", "games": 1, "win_rate": 100.0, "kda": 0.33}, {"player": "noobsuppp#noob", "region": "euw1", "games": 1, "win_rate": 100.0, "kda": 4.75}, {"player": "ALBANIAN#iLevi", "region": "euw1", "games": 1, "win_rate": 100.0, "kda": 3.25}, {"player": "Thebausffs#COOL", "region": "euw1", "games": 1, "win_rate": 100.0, "kda": 1.42}, {"player": "ZeePa#RIP", "region": "euw1", "games": 1, "win_rate": 100.0, "kda": 6.33}, {"player": "Hound#0824", "region": "kr", "games": 1, "win_rate": 0.0, "kda": 3.33}, {"player": "\uc6d0 \uc9f1#KR2", "region": "kr", "games": 1, "win_rate": 0.0, "kda": 1.43}, {"player": "Cookie#3245", "region": "kr", "games": 1, "win_rate": 0.0, "kda": 1.89}, {"player": "PerfecT#132", "region": "kr", "games": 1, "win_rate": 0.0, "kda": 0.29}, {"player": "zakozako#0321", "region": "kr", "games": 1, "win_rate": 0.0, "kda": 1.67}], "UTILITY:Taric": [{"player": "\ucd08\uacc4\ubc18#777", "region": "kr", "games": 1, "win_rate": 0.0, "kda": 1.75}, {"player": "DOSEMECI NightyN#2222", "region": "euw1", "games": 1, "win_rate": 0.0, "kda": 2.09}], "UTILITY:Ambessa": [{"player": "is for you#kr0", "region": "kr", "games": 1, "win_rate": 100.0, "kda": 2.2}], "UTILITY:Elise": [{"player": "PCS Moule frite#MIAM", "region": "euw1", "games": 2, "win_rate": 50.0, "kda": 2.5}, {"player": "\uc624 \ub298#\ubb50\uba39\uc9c0", "region": "kr", "games": 1, "win_rate": 100.0, "kda": 4.75}], "UTILITY:Nami": [{"player": "Xonxwaqdaswx#0451", "region": "kr", "games": 1, "win_rate": 100.0, "kda": 11.33}, {"player": "Jean Moulin#1943", "region": "euw1", "games": 1, "win_rate": 100.0, "kda": 7.0}, {"player": "obscure supp#0426", "region": "euw1", "games": 1, "win_rate": 100.0, "kda": 9.0}, {"player": "sspop#KR2", "region": "kr", "games": 1, "win_rate": 0.0, "kda": 3.5}], "UTILITY:Thresh": [{"player": "Let me sup#KR1", "region": "kr", "games": 1, "win_rate": 100.0, "kda": 3.6}, {"player": "noobsuppp#noob", "region": "euw1", "games": 1, "win_rate": 100.0, "kda": 3.86}, {"player": "Silent#EUW26", "region": "euw1", "games": 1, "win_rate": 0.0, "kda": 3.0}, {"player": "Sleepin all Day#EUW", "region": "euw1", "games": 1, "win_rate": 0.0, "kda": 0.33}], "UTILITY:Lulu": [{"player": "Bae Suzy#KR1", "region": "kr", "games": 1, "win_rate": 100.0, "kda": 6.25}, {"player": "sootrebor#minia", "region": "euw1", "games": 1, "win_rate": 0.0, "kda": 6.33}], "UTILITY:Karma": [{"player": "Backup#0018", "region": "euw1", "games": 1, "win_rate": 100.0, "kda": 5.0}, {"player": "noobsuppp#noob", "region": "euw1", "games": 1, "win_rate": 100.0, "kda": 7.67}, {"player": "Witt#123", "region": "kr", "games": 1, "win_rate": 0.0, "kda": 1.67}, {"player": "the sky tonight#rit", "region": "euw1", "games": 1, "win_rate": 0.0, "kda": 2.38}], "UTILITY:Sylas": [{"player": "OnPi#\uc628 \ud53c", "region": "kr", "games": 1, "win_rate": 100.0, "kda": 2.5}, {"player": "TheHank#\u53cd\u8ff7\u4f60", "region": "kr", "games": 1, "win_rate": 0.0, "kda": 0.44}], "UTILITY:Poppy": [{"player": "ozzs#ozzs", "region": "kr", "games": 1, "win_rate": 0.0, "kda": 1.83}], "UTILITY:Alistar": [{"player": "xiaolongxia#3223", "region": "euw1", "games": 1, "win_rate": 100.0, "kda": 4.33}, {"player": "Felony For Abuse#EUW", "region": "euw1", "games": 1, "win_rate": 100.0, "kda": 9.5}, {"player": "clicking forward#12321", "region": "euw1", "games": 1, "win_rate": 100.0, "kda": 5.67}, {"player": "\u534e\u4e3a\u4e2d\u5355#ltz", "region": "kr", "games": 1, "win_rate": 0.0, "kda": 0.25}], "UTILITY:Bard": [{"player": "\ub315\uccad\uc787#KR123", "region": "kr", "games": 1, "win_rate": 100.0, "kda": 4.17}, {"player": "Faker#\uad6c\ub77c\ud2f0", "region": "kr", "games": 1, "win_rate": 100.0, "kda": 0.0}, {"player": "sootrebor#minia", "region": "euw1", "games": 1, "win_rate": 100.0, "kda": 2.4}, {"player": "\uc0b0\uba741#KR11", "region": "kr", "games": 1, "win_rate": 0.0, "kda": 0.71}, {"player": "qweasdqweasdqw#KR1", "region": "kr", "games": 1, "win_rate": 0.0, "kda": 0.2}, {"player": "\uc544\ub9ac\ub3c4\ub85d#asd", "region": "kr", "games": 1, "win_rate": 0.0, "kda": 1.07}, {"player": "G2 Labrov#8085", "region": "euw1", "games": 1, "win_rate": 0.0, "kda": 2.0}], "UTILITY:Shen": [{"player": "yuedu#KR1", "region": "kr", "games": 1, "win_rate": 100.0, "kda": 6.25}, {"player": "\uc774\uc0c1\ud55c\uc11c\ud3ec\ud130\uc774\uac74\uc774#KR10", "region": "kr", "games": 1, "win_rate": 100.0, "kda": 2.57}, {"player": "mtrngrxsyl#6146", "region": "kr", "games": 1, "win_rate": 0.0, "kda": 3.5}, {"player": "T1 \uad6c\ub984#2007", "region": "kr", "games": 1, "win_rate": 0.0, "kda": 2.11}, {"player": "Bluffing#1207", "region": "kr", "games": 1, "win_rate": 0.0, "kda": 2.14}, {"player": "Stendinho 10#lrd", "region": "euw1", "games": 1, "win_rate": 0.0, "kda": 0.87}], "UTILITY:Milio": [{"player": "mtrngrxsyl#6146", "region": "kr", "games": 1, "win_rate": 100.0, "kda": 3.75}], "UTILITY:Nautilus": [{"player": "Bisgaard#Mid", "region": "euw1", "games": 2, "win_rate": 0.0, "kda": 0.89}, {"player": "\ub315\uccad\uc787#KR123", "region": "kr", "games": 1, "win_rate": 100.0, "kda": 4.38}, {"player": "bai se zh1 chuan#qwe1", "region": "kr", "games": 1, "win_rate": 100.0, "kda": 3.2}, {"player": "T1 \uc5d0\ud14c\ub974#1225", "region": "kr", "games": 1, "win_rate": 0.0, "kda": 2.0}, {"player": "Xonxwaqdaswx#0451", "region": "kr", "games": 1, "win_rate": 0.0, "kda": 0.0}], "UTILITY:Rumble": [{"player": "zakozako#0321", "region": "kr", "games": 1, "win_rate": 0.0, "kda": 0.2}], "UTILITY:Skarner": [{"player": "dy\u665a\u661f\u767d#bin", "region": "kr", "games": 1, "win_rate": 100.0, "kda": 3.0}], "UTILITY:Senna": [{"player": "Teddy#sss", "region": "kr", "games": 1, "win_rate": 100.0, "kda": 3.83}, {"player": "\ud55c\uad6d\uc778\uc774 \uc544\ub2c8\ub2e4#EUW0", "region": "euw1", "games": 1, "win_rate": 100.0, "kda": 3.0}, {"player": "Gottschalck#EUW", "region": "euw1", "games": 1, "win_rate": 0.0, "kda": 1.71}, {"player": "Gunfire#ADC3", "region": "euw1", "games": 1, "win_rate": 0.0, "kda": 1.36}], "UTILITY:Rell": [{"player": "Jean Moulin#1943", "region": "euw1", "games": 1, "win_rate": 100.0, "kda": 9.5}, {"player": "wadwaaer#wywq", "region": "kr", "games": 1, "win_rate": 0.0, "kda": 7.0}], "UTILITY:Syndra": [{"player": "Fzz gege#KR11", "region": "kr", "games": 1, "win_rate": 0.0, "kda": 1.91}], "UTILITY:Leona": [{"player": "Nuyoah#2077", "region": "kr", "games": 1, "win_rate": 100.0, "kda": 18.0}, {"player": "\u5929\u4e0b\u6b66\u529f \u552f\u5feb\u4e0d\u7834#kr11", "region": "kr", "games": 1, "win_rate": 100.0, "kda": 3.83}, {"player": "KRX AKaJe#MUR", "region": "kr", "games": 1, "win_rate": 100.0, "kda": 3.8}, {"player": "PCS Moule frite#MIAM", "region": "euw1", "games": 1, "win_rate": 100.0, "kda": 3.0}, {"player": "ALBANIAN#iLevi", "region": "euw1", "games": 1, "win_rate": 100.0, "kda": 2.0}, {"player": "JDS 2115#EUW", "region": "euw1", "games": 1, "win_rate": 0.0, "kda": 0.67}, {"player": "CANDYYY#SRB", "region": "euw1", "games": 1, "win_rate": 0.0, "kda": 1.67}], "UTILITY:Rakan": [{"player": "\uc774\uc0c1\ud55c\uc11c\ud3ec\ud130\uc774\uac74\uc774#KR10", "region": "kr", "games": 1, "win_rate": 100.0, "kda": 5.33}, {"player": "\ucd5c\uc6b0\uc81c#\uc18c\ub9ac\uafbc", "region": "euw1", "games": 1, "win_rate": 0.0, "kda": 1.11}], "UTILITY:Seraphine": [{"player": "Nunnista#SYK", "region": "euw1", "games": 1, "win_rate": 100.0, "kda": 5.4}, {"player": "Nyulia Lover#DEAD", "region": "euw1", "games": 1, "win_rate": 100.0, "kda": 4.4}, {"player": "Kotoha#\u30cf\u30b3\u30ea\u30ea", "region": "kr", "games": 1, "win_rate": 0.0, "kda": 2.56}, {"player": "Trobax#EUW2", "region": "euw1", "games": 1, "win_rate": 0.0, "kda": 2.5}], "TOP:Malphite": [{"player": "Shadowliner#444", "region": "euw1", "games": 1, "win_rate": 0.0, "kda": 0.67}], "TOP:Rengar": [{"player": "Grand Regent#\u592902", "region": "euw1", "games": 1, "win_rate": 0.0, "kda": 3.57}], "TOP:Vladimir": [{"player": "AstroSwag#MEOW", "region": "euw1", "games": 1, "win_rate": 100.0, "kda": 4.0}, {"player": "dream#dasha", "region": "euw1", "games": 1, "win_rate": 100.0, "kda": 9.0}, {"player": "Queen Pla\u010dkov\u00e1#DROGY", "region": "euw1", "games": 1, "win_rate": 0.0, "kda": 1.14}], "TOP:Fiora": [{"player": "Govno Smrdljivo#GOVNO", "region": "euw1", "games": 1, "win_rate": 100.0, "kda": 2.0}, {"player": "\u57ce\u90ca\u7267\u7b1b\u58f0#0404", "region": "euw1", "games": 1, "win_rate": 100.0, "kda": 7.67}, {"player": "Xfioramaster18#lockd", "region": "euw1", "games": 1, "win_rate": 0.0, "kda": 1.1}], "TOP:Zeri": [{"player": "TwTv LadicusVibe#Vayne", "region": "euw1", "games": 1, "win_rate": 0.0, "kda": 0.2}], "TOP:Chogath": [{"player": "TwTv TaytoLOL#TOP", "region": "euw1", "games": 1, "win_rate": 0.0, "kda": 2.6}], "TOP:Annie": [{"player": "Annie IRL#Annie", "region": "euw1", "games": 2, "win_rate": 100.0, "kda": 2.18}], "TOP:Sejuani": [{"player": "Lapishorcux#EUW", "region": "euw1", "games": 1, "win_rate": 0.0, "kda": 2.29}], "TOP:Velkoz": [{"player": "120903AN#EUWW", "region": "euw1", "games": 1, "win_rate": 100.0, "kda": 8.33}], "TOP:Ornn": [{"player": "Obsess#2308", "region": "euw1", "games": 1, "win_rate": 100.0, "kda": 1.2}, {"player": "Nireo#1408", "region": "euw1", "games": 1, "win_rate": 100.0, "kda": 5.0}], "TOP:Vex": [{"player": "Jakob Schubert#NLYUP", "region": "euw1", "games": 1, "win_rate": 0.0, "kda": 0.0}], "TOP:Yasuo": [{"player": "dodonadodo#EAST", "region": "euw1", "games": 1, "win_rate": 0.0, "kda": 2.0}], "TOP:Fizz": [{"player": "Revan#drk", "region": "euw1", "games": 1, "win_rate": 0.0, "kda": 1.5}], "TOP:Ezreal": [{"player": "\u591csnowpoem#love", "region": "euw1", "games": 1, "win_rate": 0.0, "kda": 1.0}], "TOP:Elise": [{"player": "TTV Mandarynnn#guwno", "region": "euw1", "games": 1, "win_rate": 100.0, "kda": 4.0}], "TOP:Camille": [{"player": "Alu#74747", "region": "euw1", "games": 1, "win_rate": 0.0, "kda": 3.5}], "TOP:Singed": [{"player": "Lesbian princess#UwU", "region": "euw1", "games": 1, "win_rate": 100.0, "kda": 4.0}], "TOP:Draven": [{"player": "\u5bb3\u6015999#hirm", "region": "euw1", "games": 1, "win_rate": 0.0, "kda": 0.82}], "TOP:Akshan": [{"player": "30pushupperdeath#hard", "region": "euw1", "games": 1, "win_rate": 0.0, "kda": 2.33}], "JUNGLE:Mordekaiser": [{"player": "Polish LeBron#EUW69", "region": "euw1", "games": 1, "win_rate": 100.0, "kda": 3.5}], "JUNGLE:MonkeyKing": [{"player": "\u039bMBUSH#12133", "region": "euw1", "games": 1, "win_rate": 100.0, "kda": 12.0}, {"player": "Titani\u00e2#OMG", "region": "euw1", "games": 1, "win_rate": 0.0, "kda": 0.78}, {"player": "EMPEROR AGURIN#ROYAL", "region": "euw1", "games": 1, "win_rate": 0.0, "kda": 0.0}], "JUNGLE:Khazix": [{"player": "Yukino7#cat", "region": "euw1", "games": 1, "win_rate": 100.0, "kda": 9.0}, {"player": "he is god#71300", "region": "euw1", "games": 1, "win_rate": 100.0, "kda": 5.0}, {"player": "detdert jg acc#RANK1", "region": "euw1", "games": 1, "win_rate": 100.0, "kda": 2.56}, {"player": "Lapishorcux#EUW", "region": "euw1", "games": 1, "win_rate": 0.0, "kda": 1.17}], "JUNGLE:DrMundo": [{"player": "twtv ALLXlol#78901", "region": "euw1", "games": 1, "win_rate": 100.0, "kda": 3.0}, {"player": "EL MATADOR JANIS#270", "region": "euw1", "games": 1, "win_rate": 100.0, "kda": 11.0}, {"player": "Afroboi#depu", "region": "euw1", "games": 1, "win_rate": 0.0, "kda": 2.67}], "JUNGLE:Evelynn": [{"player": "HOPE#EVE", "region": "euw1", "games": 1, "win_rate": 0.0, "kda": 0.83}], "JUNGLE:Rengar": [{"player": "\u00dfl\u00f8dre\u00efna#100", "region": "euw1", "games": 1, "win_rate": 100.0, "kda": 5.0}, {"player": "DOSEMECI NightyN#2222", "region": "euw1", "games": 1, "win_rate": 0.0, "kda": 0.5}], "JUNGLE:Udyr": [{"player": "sensiz olmaz#recep", "region": "euw1", "games": 1, "win_rate": 100.0, "kda": 3.0}], "JUNGLE:Shaco": [{"player": "MadScientist#TTV", "region": "euw1", "games": 1, "win_rate": 100.0, "kda": 21.0}, {"player": "theJuicyFruitz#EUW", "region": "euw1", "games": 1, "win_rate": 100.0, "kda": 3.33}], "JUNGLE:Pantheon": [{"player": "sknahS#rory", "region": "euw1", "games": 1, "win_rate": 100.0, "kda": 7.0}, {"player": "DOSEMECI NightyN#2222", "region": "euw1", "games": 1, "win_rate": 100.0, "kda": 3.75}], "JUNGLE:Neeko": [{"player": "emiliana#wckd", "region": "euw1", "games": 1, "win_rate": 0.0, "kda": 3.75}], "JUNGLE:Quinn": [{"player": "zng zng zng#11111", "region": "euw1", "games": 1, "win_rate": 0.0, "kda": 4.2}], "JUNGLE:Diana": [{"player": "\u00ba\u00ba\u00ba Ranger \u00ba\u00ba\u00ba#EUW", "region": "euw1", "games": 1, "win_rate": 0.0, "kda": 1.1}], "JUNGLE:Shyvana": [{"player": "EMPEROR AGURIN#ROYAL", "region": "euw1", "games": 1, "win_rate": 100.0, "kda": 4.0}], "JUNGLE:Briar": [{"player": "taru641#7489", "region": "euw1", "games": 1, "win_rate": 0.0, "kda": 2.14}], "MIDDLE:Jayce": [{"player": "Nano#AFW", "region": "euw1", "games": 1, "win_rate": 100.0, "kda": 11.0}, {"player": "indoor fish#EUW", "region": "euw1", "games": 1, "win_rate": 0.0, "kda": 1.5}], "MIDDLE:Irelia": [{"player": "Nevir#batat", "region": "euw1", "games": 1, "win_rate": 100.0, "kda": 8.0}, {"player": "\ucd5c\uc6b0\uc81c#\uc18c\ub9ac\uafbc", "region": "euw1", "games": 1, "win_rate": 100.0, "kda": 2.0}], "MIDDLE:Teemo": [{"player": "AitchAre#6767", "region": "euw1", "games": 1, "win_rate": 0.0, "kda": 1.5}], "MIDDLE:Swain": [{"player": "ComeBackFromHell#Back", "region": "euw1", "games": 1, "win_rate": 0.0, "kda": 1.2}], "MIDDLE:Neeko": [{"player": "emiliana#wckd", "region": "euw1", "games": 1, "win_rate": 100.0, "kda": 7.5}], "MIDDLE:Veigar": [{"player": "star zall#twtv", "region": "euw1", "games": 2, "win_rate": 50.0, "kda": 3.7}], "MIDDLE:Twitch": [{"player": "TwTv LadicusVibe#Vayne", "region": "euw1", "games": 1, "win_rate": 0.0, "kda": 0.83}], "MIDDLE:Anivia": [{"player": "Relative#00003", "region": "euw1", "games": 2, "win_rate": 0.0, "kda": 1.86}, {"player": "Po Gap#EUW", "region": "euw1", "games": 1, "win_rate": 100.0, "kda": 3.17}], "MIDDLE:Singed": [{"player": "Igrek#Fem", "region": "euw1", "games": 1, "win_rate": 100.0, "kda": 5.4}], "MIDDLE:Tryndamere": [{"player": "Mr useful#361", "region": "euw1", "games": 1, "win_rate": 100.0, "kda": 9.0}], "MIDDLE:Smolder": [{"player": "i miss csgo#1481", "region": "euw1", "games": 1, "win_rate": 100.0, "kda": 5.0}, {"player": "Last Dance#meow", "region": "euw1", "games": 1, "win_rate": 0.0, "kda": 2.2}], "MIDDLE:Sion": [{"player": "CROmpir#11111", "region": "euw1", "games": 1, "win_rate": 0.0, "kda": 2.83}], "MIDDLE:Leblanc": [{"player": "qpsmdnfgbh#00x", "region": "euw1", "games": 1, "win_rate": 0.0, "kda": 2.25}], "BOTTOM:Vladimir": [{"player": "Hypergamy slayer#true", "region": "euw1", "games": 1, "win_rate": 0.0, "kda": 0.5}], "BOTTOM:Vayne": [{"player": "ZYB gen4#KR01", "region": "euw1", "games": 1, "win_rate": 100.0, "kda": 8.0}, {"player": "Bobby likes adc#flex", "region": "euw1", "games": 1, "win_rate": 0.0, "kda": 3.5}], "BOTTOM:Draven": [{"player": "SLENDOOOO#DAC", "region": "euw1", "games": 1, "win_rate": 100.0, "kda": 4.5}, {"player": "obscure supp#0426", "region": "euw1", "games": 1, "win_rate": 100.0, "kda": 2.22}], "BOTTOM:Nilah": [{"player": "Serenity#2551", "region": "euw1", "games": 1, "win_rate": 0.0, "kda": 0.6}], "BOTTOM:Yasuo": [{"player": "Gala\u021bi#77251", "region": "euw1", "games": 2, "win_rate": 100.0, "kda": 2.31}], "BOTTOM:Karthus": [{"player": "regate#EUW12", "region": "euw1", "games": 1, "win_rate": 0.0, "kda": 1.5}], "BOTTOM:Samira": [{"player": "Aristotelis#GRE", "region": "euw1", "games": 1, "win_rate": 100.0, "kda": 1.67}, {"player": "elektrikgittiknk#EUW", "region": "euw1", "games": 1, "win_rate": 0.0, "kda": 1.5}], "BOTTOM:Taliyah": [{"player": "SeXnS#SeXnS", "region": "euw1", "games": 1, "win_rate": 100.0, "kda": 3.0}], "BOTTOM:Caitlyn": [{"player": "Last rite#final", "region": "euw1", "games": 1, "win_rate": 100.0, "kda": 6.5}, {"player": "detdert adc acc#RANK1", "region": "euw1", "games": 1, "win_rate": 0.0, "kda": 0.44}], "BOTTOM:Senna": [{"player": "Sergeant Sona#KJP", "region": "euw1", "games": 1, "win_rate": 100.0, "kda": 4.5}], "BOTTOM:KogMaw": [{"player": "Abner#EUW0", "region": "euw1", "games": 1, "win_rate": 0.0, "kda": 2.0}], "BOTTOM:MissFortune": [{"player": "Notiko#EUW01", "region": "euw1", "games": 1, "win_rate": 100.0, "kda": 2.67}], "BOTTOM:TwistedFate": [{"player": "Jo\u00e3o#FREAK", "region": "euw1", "games": 1, "win_rate": 0.0, "kda": 2.0}], "BOTTOM:Seraphine": [{"player": "BRANDY NITTI#MOTHR", "region": "euw1", "games": 1, "win_rate": 100.0, "kda": 2.8}], "BOTTOM:Fiora": [{"player": "Xfioramaster18#lockd", "region": "euw1", "games": 1, "win_rate": 100.0, "kda": 1.83}], "BOTTOM:Malphite": [{"player": "Jo\u00e3o#FREAK", "region": "euw1", "games": 1, "win_rate": 0.0, "kda": 2.0}], "BOTTOM:Veigar": [{"player": "Peter Decker#Argu", "region": "euw1", "games": 1, "win_rate": 100.0, "kda": 3.33}], "BOTTOM:Heimerdinger": [{"player": "Mystogan#DING", "region": "euw1", "games": 1, "win_rate": 100.0, "kda": 3.33}], "BOTTOM:Lux": [{"player": "TwT#EUW", "region": "euw1", "games": 1, "win_rate": 0.0, "kda": 2.2}], "BOTTOM:Velkoz": [{"player": "120903AN#EUWW", "region": "euw1", "games": 1, "win_rate": 0.0, "kda": 3.67}], "UTILITY:Neeko": [{"player": "Trobax#EUW2", "region": "euw1", "games": 1, "win_rate": 100.0, "kda": 3.33}], "UTILITY:Blitzcrank": [{"player": "Kaori#EUW33", "region": "euw1", "games": 1, "win_rate": 100.0, "kda": 11.0}], "UTILITY:Soraka": [{"player": "ComboScriptXD#EUW", "region": "euw1", "games": 1, "win_rate": 100.0, "kda": 2.86}, {"player": "ShadowZer\u00f4#2805", "region": "euw1", "games": 1, "win_rate": 0.0, "kda": 3.25}], "UTILITY:Janna": [{"player": "obscure supp#0426", "region": "euw1", "games": 1, "win_rate": 100.0, "kda": 4.33}], "UTILITY:Annie": [{"player": "Annie IRL#Annie", "region": "euw1", "games": 1, "win_rate": 100.0, "kda": 13.0}], "UTILITY:Leblanc": [{"player": "NoGodComplex#back", "region": "euw1", "games": 1, "win_rate": 100.0, "kda": 11.0}], "UTILITY:Zilean": [{"player": "Felony For Abuse#EUW", "region": "euw1", "games": 1, "win_rate": 0.0, "kda": 6.25}], "UTILITY:Sona": [{"player": "reo#peace", "region": "euw1", "games": 1, "win_rate": 0.0, "kda": 3.83}], "UTILITY:Braum": [{"player": "kiss the bush#S2XXX", "region": "euw1", "games": 1, "win_rate": 0.0, "kda": 2.67}], "UTILITY:Zoe": [{"player": "Danos#Danos", "region": "euw1", "games": 1, "win_rate": 0.0, "kda": 0.8}]}}